3/miselanea_ejemplos/ejemplo6/fulladder.vhd
library IEEE;
use IEEE.STD_LOGIC_1164.all;

entity fulladder is
	port(a, b, cin : in  STD_LOGIC;
	     s, cout   : out STD_LOGIC);
end;

architecture synth of fulladder is
	signal p, g : STD_LOGIC;
begin
	p    <= a xor b;
	g    <= a and b;
	s    <= p xor cin;
	cout <= g or (p and cin);
end;

3/miselanea_ejemplos/ejemplo6/fulladder_tb.vhd
library ieee;
use ieee.std_logic_1164.all;
use ieee.numeric_std.all;
use ieee.std_logic_arith.all;
use ieee.std_logic_unsigned.all;

entity fulladder_tb is
end entity fulladder_tb;

architecture RTL of fulladder_tb is
	component fulladder
		port(
			a, b, cin : in  STD_LOGIC;
			s, cout   : out STD_LOGIC
		);
	end component fulladder;

	signal vector_inputs : std_logic_vector(2 downto 0) := "000";
	signal cout          : std_logic;
	signal s             : std_logic;

	constant T : time := 10 ns;

begin

	DUT : fulladder
		port map(
			a    => vector_inputs(2),
			b    => vector_inputs(1),
			cin  => vector_inputs(0),
			s    => s,
			cout => cout
		);

	stimulus : process is
	begin
		for i in 0 to 7 loop
			vector_inputs <= vector_inputs + '1';
            wait for T;
		end loop;
        wait;
	end process stimulus;

end architecture RTL;

3/miselanea_ejemplos/ejemplo6/fulladder_wf.vcd
$date
  Thu Mar 26 23:05:55 2020
$end
$version
  GHDL v0
$end
$timescale
  1 fs
$end
$scope module standard $end
$upscope $end
$scope module std_logic_1164 $end
$upscope $end
$scope module numeric_std $end
$upscope $end
$scope module std_logic_arith $end
$upscope $end
$scope module std_logic_unsigned $end
$upscope $end
$scope module fulladder_tb $end
$var reg 3 ! vector_inputs[2:0] $end
$var reg 1 " cout $end
$var reg 1 # s $end
$scope module dut $end
$var reg 1 $ a $end
$var reg 1 % b $end
$var reg 1 & cin $end
$var reg 1 ' s $end
$var reg 1 ( cout $end
$var reg 1 ) p $end
$var reg 1 * g $end
$upscope $end
$upscope $end
$enddefinitions $end
#0
b001 !
0"
1#
0$
0%
1&
1'
0(
0)
0*
#10000000
b010 !
1#
1%
0&
1'
1)
#20000000
b011 !
1"
0#
1&
0'
1(
#30000000
b100 !
0"
1#
1$
0%
0&
1'
0(
#40000000
b101 !
1"
0#
1&
0'
1(
#50000000
b110 !
1"
0#
1%
0&
0'
1(
0)
1*
#60000000
b111 !
1#
1&
1'
#70000000
b000 !
0"
0#
0$
0%
0&
0'
0(
0*
