3/miselanea_ejemplos/ejemplo18/decoder.vhd
library IEEE;
use IEEE.STD_LOGIC_1164.all;
use IEEE.NUMERIC_STD_UNSIGNED.all;

entity decoder is
	generic(N : integer := 3);
	port(a : in  STD_LOGIC_VECTOR(N - 1 downto 0);
	     y : out STD_LOGIC_VECTOR(2**N - 1 downto 0));
end;
architecture synth of decoder is
begin
	process(all)
	begin
		y                <= (OTHERS => '0');
		y(TO_INTEGER(a)) <= '1';
	end process;
end;

3/miselanea_ejemplos/ejemplo18/decoder_tb.vhd
library ieee;
use ieee.std_logic_1164.all;
use ieee.numeric_std.all;
use IEEE.NUMERIC_STD_UNSIGNED.all;

entity decoder_tb is
end entity decoder_tb;

architecture RTL of decoder_tb is

	constant WIDTH : integer := 3;
	constant T     : time    := 10 ns;

	component decoder
		generic(N : integer);
		port(
			a : in  STD_LOGIC_VECTOR(N - 1 downto 0);
			y : out STD_LOGIC_VECTOR(2**N - 1 downto 0)
		);
	end component decoder;

	signal a : std_logic_vector(WIDTH - 1 downto 0) := (others => '0');
	signal y : std_logic_vector(2**WIDTH - 1 downto 0);

begin

	DUT : decoder
		generic map(
			N => WIDTH
		)
		port map(
			a => a,
			y => y
		);

	stimulus : process is
	begin
		for i in 0 to 2**WIDTH - 1 loop
			wait for T;
			a <= a + '1';
		end loop;
		wait for T;
		wait;
	end process stimulus;

end architecture RTL;

3/miselanea_ejemplos/ejemplo18/decoder_wf.vcd
$date
  Fri Mar 27 17:54:44 2020
$end
$version
  GHDL v0
$end
$timescale
  1 fs
$end
$scope module standard $end
$upscope $end
$scope module textio $end
$upscope $end
$scope module std_logic_1164 $end
$upscope $end
$scope module numeric_std $end
$upscope $end
$scope module numeric_std_unsigned $end
$upscope $end
$scope module decoder_tb $end
$var reg 3 ! a[2:0] $end
$var reg 8 " y[7:0] $end
$scope module dut $end
$var reg 3 # a[2:0] $end
$var reg 8 $ y[7:0] $end
$upscope $end
$upscope $end
$enddefinitions $end
#0
b000 !
b00000001 "
b000 #
b00000001 $
#10000000
b001 !
b00000010 "
b001 #
b00000010 $
#20000000
b010 !
b00000100 "
b010 #
b00000100 $
#30000000
b011 !
b00001000 "
b011 #
b00001000 $
#40000000
b100 !
b00010000 "
b100 #
b00010000 $
#50000000
b101 !
b00100000 "
b101 #
b00100000 $
#60000000
b110 !
b01000000 "
b110 #
b01000000 $
#70000000
b111 !
b10000000 "
b111 #
b10000000 $
#80000000
b000 !
b00000001 "
b000 #
b00000001 $
