3/ejemplos_xilinx/Lab3-1-2/decoder_3to8_dataflow.vhd
--------------------------------------------
-- Module Name: decoder_3to8_dataflow
--------------------------------------------

library IEEE;
use IEEE.STD_LOGIC_1164.ALL;

-- library UNISIM;
-- use UNISIM.VComponents.all;

Entity decoder_3to8_dataflow Is
port(
		x 	: in STD_LOGIC_VECTOR(2 downto 0);
		y	: out STD_LOGIC_VECTOR(7 downto 0)
	);
end decoder_3to8_dataflow;

Architecture behavior of decoder_3to8_dataflow Is
	
begin

	y(0) <= not(x(2) or x(1) or x(0));	 
	y(1) <= (x(2) and not(x(1)) and not(x(0)));
	y(2) <= (not(x(2)) and x(1) and not(x(0)));
	y(3) <= (x(2) and x(1) and not(x(0)));
	y(4) <= (not(x(2)) and not(x(1)) and x(0));
	y(5) <= (x(2) and not(x(1)) and x(0));
	y(6) <= (not(x(2)) and x(1) and x(0));
	y(7) <= (x(2) and x(1) and x(0));
	
end behavior;

3/ejemplos_xilinx/Lab3-1-2/decoder_74138_dataflow.vhd
--------------------------------------------
-- Module Name: decoder_74138_dataflow
--------------------------------------------

library IEEE; 
use IEEE.STD_LOGIC_1164.ALL;

-- library UNISIM;
-- use UNISIM.VComponents.all;

Entity decoder_74138_dataflow Is
port(
		g1  : in STD_LOGIC;
		g2a_n : in STD_LOGIC;
		g2b_n : in STD_LOGIC;
		x 	: in STD_LOGIC_VECTOR(2 downto 0);
		y	: out STD_LOGIC_VECTOR(7 downto 0)
	);
end decoder_74138_dataflow;

Architecture behavior of decoder_74138_dataflow Is
	Component decoder_3to8_dataflow
	port (
		x 		: in STD_LOGIC_VECTOR (2 downto 0);
		y 		: out STD_LOGIC_VECTOR (7 downto 0)
	);	
	End Component;
	
	Signal enable : STD_LOGIC;
	Signal y_int  : STD_LOGIC_VECTOR(7 downto 0);
	Signal reverse_x : STD_LOGIC_VECTOR(2 downto 0);	
	
begin
	U1:  decoder_3to8_dataflow PORT MAP (
			x => reverse_x,
			y => y_int
		 );

	reverse_x(2) <= x(0);
	reverse_x(1) <= x(1);
	reverse_x(0) <= x(2);
	enable <= (g1 and not(g2a_n) and not(g2b_n));

process (enable) begin	
	if (enable = '1') then
		y <= not(y_int);
	else
		y <= "11111111";
	end if;
end process;
	
end behavior;

3/ejemplos_xilinx/Lab3-1-2/decoder_74138_dataflow_tb.vhd
--------------------------------------------
-- Module Name: decoder_74138_dataflow_tb
--------------------------------------------

library IEEE;
use IEEE.STD_LOGIC_1164.ALL;
use IEEE.STD_LOGIC_ARITH.ALL;
use IEEE.STD_LOGIC_UNSIGNED.ALL;

-- library UNISIM;
-- use UNISIM.VComponents.all;

Entity decoder_74138_dataflow_tb Is
end decoder_74138_dataflow_tb;

Architecture behavior of decoder_74138_dataflow_tb Is
	Component decoder_74138_dataflow
	port(
		g1  : in STD_LOGIC;
		g2a_n : in STD_LOGIC;
		g2b_n : in STD_LOGIC;
		x 	: in STD_LOGIC_VECTOR(2 downto 0);
		y	: out STD_LOGIC_VECTOR(7 downto 0)
	);
	End Component;
	
	Signal count : STD_LOGIC_VECTOR (2 downto 0) := "000";
	Signal x 	 : STD_LOGIC_VECTOR (2 downto 0) := "000";
	Signal y 	 : STD_LOGIC_VECTOR (7 downto 0) := "00000000";
	
	Signal g1  : STD_LOGIC := '0';
    Signal g2a_n : STD_LOGIC := '0';
    Signal g2b_n : STD_LOGIC := '0';

begin
	DUT:  decoder_74138_dataflow PORT MAP (
			g1 => g1,
			g2a_n => g2a_n,
			g2b_n => g2b_n,
			x => x,
			y => y
		 );
		 
	process
		variable k : integer := 0;

	begin
		
		x <= "000"; g1 <= '0'; g2a_n <= '1'; g2b_n <= '1';
        for k in 0 to 7 loop         

		  wait for 5 ns;
		  x <= count;
		  
		  wait for 10 ns;
        end loop;		 

		x <= "000"; g1 <= '1'; g2a_n <= '0'; g2b_n <= '1';
        for k in 0 to 7 loop         

		  wait for 5 ns;
		  x <= count;
		  
		  wait for 10 ns;
        end loop;	
		
		x <= "000"; g1 <= '0'; g2a_n <= '1'; g2b_n <= '0';
        for k in 0 to 7 loop         

		  wait for 5 ns;
		  x <= count;
		  
		  wait for 10 ns;
        end loop;	
		
		x <= "000"; g1 <= '1'; g2a_n <= '0'; g2b_n <= '0';
        for k in 0 to 7 loop         

		  wait for 5 ns;
		  x <= count;
		  
		  wait for 10 ns;
		  count <= count + '1';
        end loop;	
		
		wait;
	end process;
end behavior;

3/ejemplos_xilinx/Lab3-1-2/decoder_74138_dataflow_tb_results.vcd
$date
  Mon Aug  5 23:59:17 2019
$end
$version
  GHDL v0
$end
$timescale
  1 fs
$end
$scope module standard $end
$upscope $end
$scope module std_logic_1164 $end
$upscope $end
$scope module std_logic_arith $end
$upscope $end
$scope module std_logic_unsigned $end
$upscope $end
$scope module decoder_74138_dataflow_tb $end
$var reg 3 ! count[2:0] $end
$var reg 3 " x[2:0] $end
$var reg 8 # y[7:0] $end
$var reg 1 $ g1 $end
$var reg 1 % g2a_n $end
$var reg 1 & g2b_n $end
$scope module dut $end
$var reg 1 ' g1 $end
$var reg 1 ( g2a_n $end
$var reg 1 ) g2b_n $end
$var reg 3 * x[2:0] $end
$var reg 8 + y[7:0] $end
$var reg 1 , enable $end
$var reg 8 - y_int[7:0] $end
$var reg 3 . reverse_x[2:0] $end
$scope module u1 $end
$var reg 3 / x[2:0] $end
$var reg 8 0 y[7:0] $end
$upscope $end
$upscope $end
$upscope $end
$enddefinitions $end
#0
b000 !
b000 "
b11111111 #
0$
1%
1&
0'
1(
1)
b000 *
b11111111 +
0,
b00000001 -
b000 .
b000 /
b00000001 0
#5000000
#15000000
#20000000
#30000000
#35000000
#45000000
#50000000
#60000000
#65000000
#75000000
#80000000
#90000000
#95000000
#105000000
#110000000
#120000000
1$
0%
1'
0(
#125000000
#135000000
#140000000
#150000000
#155000000
#165000000
#170000000
#180000000
#185000000
#195000000
#200000000
#210000000
#215000000
#225000000
#230000000
#240000000
0$
1%
0&
0'
1(
0)
#245000000
#255000000
#260000000
#270000000
#275000000
#285000000
#290000000
#300000000
#305000000
#315000000
#320000000
#330000000
#335000000
#345000000
#350000000
#360000000
b11111110 #
1$
0%
1'
0(
b11111110 +
1,
#365000000
#375000000
b001 !
#380000000
b001 "
b001 *
b00000010 -
b100 .
b100 /
b00000010 0
#390000000
b010 !
#395000000
b010 "
b010 *
b00000100 -
b010 .
b010 /
b00000100 0
#405000000
b011 !
#410000000
b011 "
b011 *
b00001000 -
b110 .
b110 /
b00001000 0
#420000000
b100 !
#425000000
b100 "
b100 *
b00010000 -
b001 .
b001 /
b00010000 0
#435000000
b101 !
#440000000
b101 "
b101 *
b00100000 -
b101 .
b101 /
b00100000 0
#450000000
b110 !
#455000000
b110 "
b110 *
b01000000 -
b011 .
b011 /
b01000000 0
#465000000
b111 !
#470000000
b111 "
b111 *
b10000000 -
b111 .
b111 /
b10000000 0
#480000000
b000 !
