3/miselanea_ejemplos/ejemplo14/priorityckt.vhd
library IEEE;
use IEEE.STD_LOGIC_1164.all;

entity priorityckt is
	port(a : in  STD_LOGIC_VECTOR(3 downto 0);
	     y : out STD_LOGIC_VECTOR(3 downto 0));
end;

architecture synth of priorityckt is
begin
	process(all)
	begin
		if a(3) = '1' then
			y <= "1000";
		elsif a(2) = '1' then
			y <= "0100";
		elsif a(1) = '1' then
			y <= "0010";
		elsif a(0) = '1' then
			y <= "0001";
		else
			y <= "0000";
		end if;
	end process;
end;

3/miselanea_ejemplos/ejemplo14/priorityckt_tb.vhd
library ieee;
use ieee.std_logic_1164.all;
use ieee.numeric_std.all;
use ieee.numeric_std_unsigned.all;

entity priorityckt_tb is
end entity priorityckt_tb;

architecture RTL of priorityckt_tb is
	component priorityckt
		port(
			a : in  STD_LOGIC_VECTOR(3 downto 0);
			y : out STD_LOGIC_VECTOR(3 downto 0)
		);
	end component priorityckt;
	
	signal a : std_logic_vector(3 downto 0) := "0000";
	signal y : std_logic_vector(3 downto 0);
	constant T : time := 10 ns;
	
begin
	
	DUT: priorityckt
		port map(
			a => a,
			y => y
		);
		
	stimulus : process is
	begin
		for i in 0 to 15 loop
			wait for T;
			a <= a + '1';
		end loop;
		wait;
	end process stimulus;
	

end architecture RTL;

3/miselanea_ejemplos/ejemplo14/priorityckt_wf.vcd
$date
  Fri Mar 27 09:46:08 2020
$end
$version
  GHDL v0
$end
$timescale
  1 fs
$end
$scope module standard $end
$upscope $end
$scope module textio $end
$upscope $end
$scope module std_logic_1164 $end
$upscope $end
$scope module numeric_std $end
$upscope $end
$scope module numeric_std_unsigned $end
$upscope $end
$scope module priorityckt_tb $end
$var reg 4 ! a[3:0] $end
$var reg 4 " y[3:0] $end
$scope module dut $end
$var reg 4 # a[3:0] $end
$var reg 4 $ y[3:0] $end
$upscope $end
$upscope $end
$enddefinitions $end
#0
b0000 !
b0000 "
b0000 #
b0000 $
#10000000
b0001 !
b0001 "
b0001 #
b0001 $
#20000000
b0010 !
b0010 "
b0010 #
b0010 $
#30000000
b0011 !
b0011 #
#40000000
b0100 !
b0100 "
b0100 #
b0100 $
#50000000
b0101 !
b0101 #
#60000000
b0110 !
b0110 #
#70000000
b0111 !
b0111 #
#80000000
b1000 !
b1000 "
b1000 #
b1000 $
#90000000
b1001 !
b1001 #
#100000000
b1010 !
b1010 #
#110000000
b1011 !
b1011 #
#120000000
b1100 !
b1100 #
#130000000
b1101 !
b1101 #
#140000000
b1110 !
b1110 #
#150000000
b1111 !
b1111 #
#160000000
b0000 !
b0000 "
b0000 #
b0000 $
