3/ejemplos_clase/ROM/rom.vhd
--------------------------------------------
-- Module Name: rom
--------------------------------------------

library IEEE;
use IEEE.STD_LOGIC_1164.ALL;

-- library UNISIM;
-- use UNISIM.VComponents.all;

Entity rom Is
generic(
		bits : integer := 8;     -- # of bits per word 
		words: integer := 8    -- # of words in the memory
       );
port(
		addr: in integer range 0 to words-1;
		data: out std_logic_vector(bits-1 downto 0)
	);
end rom;

Architecture behavior of rom is
	type vector_array is array (0 to words-1) of std_logic_vector (bits-1 downto 0);

	CONSTANT memory: vector_array := ( 
		"00000000",
		"00000010",
		"00000100",
		"00001000", 
		"00010000",
		"00100000",
		"01000000",
		"10000000");	
begin
	data <= memory(addr);
end behavior;

3/ejemplos_clase/ROM/rom_tb.vhd
--------------------------------------------
-- Module Name: rom_tb
--------------------------------------------

library IEEE;
use IEEE.STD_LOGIC_1164.ALL;
use IEEE.STD_LOGIC_ARITH.ALL;
use IEEE.STD_LOGIC_UNSIGNED.ALL;
use STD.textio.all; --for line
use IEEE.std_logic_textio.all; --for write
use ieee.numeric_std.all;


-- library UNISIM;
-- use UNISIM.VComponents.all;

Entity rom_tb Is
end rom_tb;

Architecture behavior of rom_tb Is

	CONSTANT WORDS     : integer := 8;
	CONSTANT DATA_SIZE : integer := 8;
	CONSTANT DELAY     : time := 10 ns;
	CONSTANT LEN       : integer := 3;
	
	Signal addr_s    : integer range 0 to WORDS -1;
	Signal data_s    : std_logic_vector(DATA_SIZE-1 downto 0);
	Signal addr_s2   : std_logic_vector(LEN-1 downto 0);
	
	
	Component rom Is
	generic(
			bits : integer := DATA_SIZE;
			words: integer := WORDS
		   );
	port(
			addr: in integer range 0 to WORDS-1;
			data: out std_logic_vector(DATA_SIZE -1 downto 0)
		);
	end Component;

	
	procedure expected_data (
		proc_addr : in integer range 0 to WORDS-1;
		proc_data : out std_logic_vector(DATA_SIZE -1 downto 0)) is

	type vector_array is array (0 to WORDS - 1) of std_logic_vector (DATA_SIZE-1 downto 0);

	CONSTANT memory: vector_array := ( 
			"00000000",
			"00000010",
			"00000100",
			"00001000", 
			"00010000",
			"00100000",
			"01000000",
			"10000000");
	begin	
		proc_data := memory(proc_addr);
	end expected_data;


begin

	DUT: rom 
	generic map ( 
	  bits => DATA_SIZE,
	  words => WORDS
	)
	port map (
	  addr => addr_s,
	  data => data_s
	);


	Estim: process
    begin
		--wait for DELAY;	
        for i in 0 to WORDS - 1 loop
            addr_s <= i;
            wait for DELAY;   
		end loop;
		wait;
	end process Estim;

	

	addr_s2 <= std_logic_vector(to_unsigned(addr_s, addr_s2'length)); -- Add for delay
	
	Verific: process(addr_s2)
	variable proc_data : std_logic_vector(DATA_SIZE -1 downto 0);
	variable s : line;
	begin		
		expected_data(addr_s, proc_data);
		-- If the outputs match, then announce it to the simulator console.
		if ( data_s = proc_data) then
			write (s, string'("MEMORY DATA MATCHED")); 
			writeline (output, s);
			write (s, string'("MEMORY[")); write (s, addr_s); write (s, string'("]: "));
			write (s, string'("Expected: ")); write (s, proc_data);
            write (s, string'("; Implemented: ")); write (s, data_s); 
			writeline (output, s);
		else
		    write (s, string'("MEMORY DATA MISSMATCHED")); 
		    write (s, string'("MEMORY[")); write (s, addr_s); write (s, string'("]: "));
			write (s, string'("Expected: ")); write (s, proc_data);
            write (s, string'("; Implemented: ")); write (s, data_s); 
			writeline (output, s);
		end if;	
	end process Verific; 

end behavior;

3/ejemplos_clase/ROM/rom_tb_results.vcd
$date
  Mon Aug 19 21:46:14 2019
$end
$version
  GHDL v0
$end
$timescale
  1 fs
$end
$scope module standard $end
$upscope $end
$scope module std_logic_1164 $end
$upscope $end
$scope module std_logic_arith $end
$upscope $end
$scope module std_logic_unsigned $end
$upscope $end
$scope module textio $end
$upscope $end
$scope module std_logic_textio $end
$upscope $end
$scope module numeric_std $end
$upscope $end
$scope module rom_tb $end
$var integer 32 ! addr_s $end
$var reg 8 " data_s[7:0] $end
$var reg 3 # addr_s2[2:0] $end
$scope module dut $end
$var integer 32 $ addr $end
$var reg 8 % data[7:0] $end
$upscope $end
$upscope $end
$enddefinitions $end
#0
b0 !
b00000000 "
b000 #
b0 $
b00000000 %
#10000000
b1 !
b00000010 "
b001 #
b1 $
b00000010 %
#20000000
b10 !
b00000100 "
b010 #
b10 $
b00000100 %
#30000000
b11 !
b00001000 "
b011 #
b11 $
b00001000 %
#40000000
b100 !
b00010000 "
b100 #
b100 $
b00010000 %
#50000000
b101 !
b00100000 "
b101 #
b101 $
b00100000 %
#60000000
b110 !
b01000000 "
b110 #
b110 $
b01000000 %
#70000000
b111 !
b10000000 "
b111 #
b111 $
b10000000 %
