5/example4/solucion_moore/odd_fsm_moore.vhd
library IEEE;
use IEEE.STD_LOGIC_1164.ALL;
use IEEE.NUMERIC_STD.ALL; 
use IEEE.STD_LOGIC_UNSIGNED.ALL;
use IEEE.STD_LOGIC_ARITH.ALL;

entity ODD_FSM_MOORE is
    Port ( reset : in STD_LOGIC;
           clk : in STD_LOGIC;
           x : in STD_LOGIC;
           z : out STD_LOGIC);
end ODD_FSM_MOORE;

architecture Behavioral of ODD_FSM_MOORE is

    -- declaraciones modelo FSM
    type STATES is (
                      even,     -- Estado que indica una cantidad par de 1's
                      odd       -- Estado que indica una cantidad impar de 1's
                   );
    signal state, next_state: STATES;

begin

    -------------------------------------------------------------------
    SYNC_PROC: process(clk,reset)
    begin
        if reset = '1' then
          state <= even;        
        elsif clk'event and clk='1' then
            state <= next_state;            
        end if;
    end process;

    -------------------------------------------------------------------
    OUTPUT_DECODE : process (state)
    begin
      case (state) is 
         when even =>
           z <= '0';
         when odd =>
           z <= '1';
         when others =>
           z <= '0';
      end case;
    end process;

    -------------------------------------------------------------------
    NEXT_STATE_DECODE : process(state, x)
    begin
        next_state <= even;
        case(state) is            
            when even =>
              if (x = '1') then                
                next_state <= odd;              
              end if;
            when odd =>
              if (x = '1') then       
                next_state <= even;
              else 
                next_state <= odd;
              end if;                     
        end case;
    end process;
end Behavioral;

5/example4/solucion_moore/odd_fsm_moore_tb.vhd
library IEEE;
use IEEE.STD_LOGIC_1164.ALL;
use IEEE.NUMERIC_STD.ALL; 
use IEEE.STD_LOGIC_UNSIGNED.ALL;
use IEEE.STD_LOGIC_ARITH.ALL;

entity ODD_FSM_MOORE_TB is
end ODD_FSM_MOORE_TB;

architecture Behavioral of ODD_FSM_MOORE_TB is

    -- declaraciones modelo FSM

    signal clk_int, reset_int, x_int, z_int: STD_LOGIC;   

    component ODD_FSM_MOORE is
      Port ( reset : in STD_LOGIC;
             clk : in STD_LOGIC;
             x : in STD_LOGIC;             
             z : out STD_LOGIC);
    end component;

begin

  DUT: ODD_FSM_MOORE
	Port map (
    reset => reset_int,
    clk => clk_int,
    x => x_int,
    z => z_int
  );
  

  clk_gen_proc: process
  begin
    clk_int <= '0';
    wait for 5 ns;
    clk_int <= '1';
    wait for 5 ns;
  end process clk_gen_proc;

  reset_gen_proc: process
  begin
    reset_int <= '1';
    wait for 3 ns;     -- 3 ns
    reset_int <= '0';
    wait;   
  end  process reset_gen_proc;

  data_gen_proc: process
  begin    
    x_int <= '0'; 
    wait for 30 ns;    -- 30 ns
    x_int <= '1';
    wait for 10 ns;    -- 40 ns
    x_int <= '0';
    wait for 10 ns;    -- 50 ns
    x_int <= '1';
    wait for 30 ns;    -- 80 ns
    x_int <= '0';
    wait for 20 ns;    -- 100 ns
    x_int <= '1';
    wait for 40 ns;    -- 140 ns
    x_int <= '0';
    wait for 30 ns;    -- 170 ns
    x_int <= '1';
    wait for 20 ns;    -- 190 ns
    x_int <= '0';
    wait;
  end process data_gen_proc;
   
end Behavioral;

5/example4/solucion_moore/odd_fsm_moore_tb_results.vcd
$date
  Mon Jul  6 18:38:29 2020
$end
$version
  GHDL v0
$end
$timescale
  1 fs
$end
$scope module standard $end
$upscope $end
$scope module std_logic_1164 $end
$upscope $end
$scope module numeric_std $end
$upscope $end
$scope module std_logic_arith $end
$upscope $end
$scope module std_logic_unsigned $end
$upscope $end
$scope module odd_fsm_moore_tb $end
$var reg 1 ! clk_int $end
$var reg 1 " reset_int $end
$var reg 1 # x_int $end
$var reg 1 $ z_int $end
$scope module dut $end
$var reg 1 % reset $end
$var reg 1 & clk $end
$var reg 1 ' x $end
$var reg 1 ( z $end
$comment state is not handled $end
$comment next_state is not handled $end
$upscope $end
$upscope $end
$enddefinitions $end
#0
0!
1"
0#
0$
1%
0&
0'
0(
#3000000
0"
0%
#5000000
1!
1&
#10000000
0!
0&
#15000000
1!
1&
#20000000
0!
0&
#25000000
1!
1&
#30000000
0!
1#
0&
1'
#35000000
1!
1$
1&
1(
#40000000
0!
0#
0&
0'
#45000000
1!
1&
#50000000
0!
1#
0&
1'
#55000000
1!
0$
1&
0(
#60000000
0!
0&
#65000000
1!
1$
1&
1(
#70000000
0!
0&
#75000000
1!
0$
1&
0(
#80000000
0!
0#
0&
0'
#85000000
1!
1&
#90000000
0!
0&
#95000000
1!
1&
#100000000
0!
1#
0&
1'
#105000000
1!
1$
1&
1(
#110000000
0!
0&
#115000000
1!
0$
1&
0(
#120000000
0!
0&
#125000000
1!
1$
1&
1(
#130000000
0!
0&
#135000000
1!
0$
1&
0(
#140000000
0!
0#
0&
0'
#145000000
1!
1&
#150000000
0!
0&
#155000000
1!
1&
#160000000
0!
0&
#165000000
1!
1&
#170000000
0!
1#
0&
1'
#175000000
1!
1$
1&
1(
#180000000
0!
0&
#185000000
1!
0$
1&
0(
#190000000
0!
0#
0&
0'
