3/miselanea_ejemplos/ejemplo12/seven_seg_decoder.vhd
library IEEE; 
use IEEE.STD_LOGIC_1164.all;

entity seven_seg_decoder is
  port(data: in STD_LOGIC_VECTOR(3 downto 0);
       segments: out STD_LOGIC_VECTOR(6 downto 0));
end;

architecture synth of seven_seg_decoder is
begin
  process(all) begin
case data is
  --                        abcdefg
  when X"0" => segments <= "1111110";
  when X"1" => segments <= "0110000";
  when X"2" => segments <= "1101101";
  when X"3" => segments <= "1111001";
  when X"4" => segments <= "0110011";
  when X"5" => segments <= "1011011";
  when X"6" => segments <= "1011111";
  when X"7" => segments <= "1110000";
  when X"8" => segments <= "1111111";
  when X"9" => segments <= "1110011";
  when others => segments <= "0000000";
end case;
end process;
end;

3/miselanea_ejemplos/ejemplo12/seven_seg_decoder_tb.vhd
library ieee;
use ieee.std_logic_1164.all;
use ieee.numeric_std.all;
use ieee.numeric_std_unsigned.all;

entity seven_seg_decoder_tb is
end entity seven_seg_decoder_tb;

architecture RTL of seven_seg_decoder_tb is
	component seven_seg_decoder
		port(
			data     : in  STD_LOGIC_VECTOR(3 downto 0);
			segments : out STD_LOGIC_VECTOR(6 downto 0)
		);
	end component seven_seg_decoder;
	
	signal data : std_logic_vector(3 downto 0) := "0000";
	signal segments : std_logic_vector(6 downto 0);
	
	constant T : time := 10 ns;
	
begin
	
	DUT: seven_seg_decoder
		port map(
			data     => data,
			segments => segments
		);
		
	stimulus : process is
	begin
		for i in 0 to 15 loop
			data <= data + '1';
            wait for T;
		end loop;
		wait;
	end process stimulus;
	
end architecture RTL;

3/miselanea_ejemplos/ejemplo12/seven_seg_decoder_wf.vcd
$date
  Fri Mar 27 09:23:45 2020
$end
$version
  GHDL v0
$end
$timescale
  1 fs
$end
$scope module standard $end
$upscope $end
$scope module textio $end
$upscope $end
$scope module std_logic_1164 $end
$upscope $end
$scope module numeric_std $end
$upscope $end
$scope module numeric_std_unsigned $end
$upscope $end
$scope module seven_seg_decoder_tb $end
$var reg 4 ! data[3:0] $end
$var reg 7 " segments[6:0] $end
$scope module dut $end
$var reg 4 # data[3:0] $end
$var reg 7 $ segments[6:0] $end
$upscope $end
$upscope $end
$enddefinitions $end
#0
b0001 !
b0110000 "
b0001 #
b0110000 $
#10000000
b0010 !
b1101101 "
b0010 #
b1101101 $
#20000000
b0011 !
b1111001 "
b0011 #
b1111001 $
#30000000
b0100 !
b0110011 "
b0100 #
b0110011 $
#40000000
b0101 !
b1011011 "
b0101 #
b1011011 $
#50000000
b0110 !
b1011111 "
b0110 #
b1011111 $
#60000000
b0111 !
b1110000 "
b0111 #
b1110000 $
#70000000
b1000 !
b1111111 "
b1000 #
b1111111 $
#80000000
b1001 !
b1110011 "
b1001 #
b1110011 $
#90000000
b1010 !
b0000000 "
b1010 #
b0000000 $
#100000000
b1011 !
b1011 #
#110000000
b1100 !
b1100 #
#120000000
b1101 !
b1101 #
#130000000
b1110 !
b1110 #
#140000000
b1111 !
b1111 #
#150000000
b0000 !
b1111110 "
b0000 #
b1111110 $
