3/ejemplos_xilinx/Lab3-1-1/decoder_3to8_dataflow.vhd
--------------------------------------------
-- Module Name: decoder_3to8_dataflow
--------------------------------------------

library IEEE;
use IEEE.STD_LOGIC_1164.ALL;

-- library UNISIM;
-- use UNISIM.VComponents.all;

Entity decoder_3to8_dataflow Is
port(
		x 	: in STD_LOGIC_VECTOR(2 downto 0);
		y	: out STD_LOGIC_VECTOR(7 downto 0)
	);
end decoder_3to8_dataflow;

Architecture behavior of decoder_3to8_dataflow Is
	
begin

	y(0) <= not(x(2) or x(1) or x(0));	 
	y(1) <= (not(x(2)) and not(x(1)) and x(0));
	y(2) <= (not(x(2)) and x(1) and not(x(0)));
	y(3) <= (not(x(2)) and x(1) and x(0));
	y(4) <= (x(2) and not(x(1)) and not(x(0)));
	y(5) <= (x(2) and not(x(1)) and x(0));
	y(6) <= (x(2) and x(1) and not(x(0)));
	y(7) <= (x(2) and x(1) and x(0));
	
end behavior;

3/ejemplos_xilinx/Lab3-1-1/decoder_3to8_dataflow_tb.vhd
--------------------------------------------
-- Module Name: decoder_3to8_dataflow_tb
--------------------------------------------

library IEEE;
use IEEE.STD_LOGIC_1164.ALL;
use IEEE.STD_LOGIC_ARITH.ALL;
use IEEE.STD_LOGIC_UNSIGNED.ALL;

-- library UNISIM;
-- use UNISIM.VComponents.all;

Entity decoder_3to8_dataflow_tb Is
end decoder_3to8_dataflow_tb;

Architecture behavior of decoder_3to8_dataflow_tb Is
	Component decoder_3to8_dataflow
	port (
		x 		: in STD_LOGIC_VECTOR (2 downto 0);
		y 		: out STD_LOGIC_VECTOR (7 downto 0)
	);	
	End Component;
	
	Signal x 	 : STD_LOGIC_VECTOR (2 downto 0) := "000";
	Signal y 	 : STD_LOGIC_VECTOR (7 downto 0) := "00000000";
	Signal count : STD_LOGIC_VECTOR (2 downto 0) := "000";

begin
	DUT:  decoder_3to8_dataflow PORT MAP (
			x => x,
			y => y
		 );
		 
	process
		-- variable k : integer := 0;

	begin
		
        for k in 0 to 7 loop   
    

		  wait for 5 ns;
		  x <= count;
		  
		  wait for 10 ns;
		  
        count <= count + '1';  		  
        end loop;		 
		
		wait;
	end process;
end behavior;

3/ejemplos_xilinx/Lab3-1-1/decoder_3to8_dataflow_tb_results.vcd
$date
  Mon Aug  5 23:20:51 2019
$end
$version
  GHDL v0
$end
$timescale
  1 fs
$end
$scope module standard $end
$upscope $end
$scope module std_logic_1164 $end
$upscope $end
$scope module std_logic_arith $end
$upscope $end
$scope module std_logic_unsigned $end
$upscope $end
$scope module decoder_3to8_dataflow_tb $end
$var reg 3 ! x[2:0] $end
$var reg 8 " y[7:0] $end
$var reg 3 # count[2:0] $end
$scope module dut $end
$var reg 3 $ x[2:0] $end
$var reg 8 % y[7:0] $end
$upscope $end
$upscope $end
$enddefinitions $end
#0
b000 !
b00000001 "
b000 #
b000 $
b00000001 %
#5000000
#15000000
b001 #
#20000000
b001 !
b00000010 "
b001 $
b00000010 %
#30000000
b010 #
#35000000
b010 !
b00000100 "
b010 $
b00000100 %
#45000000
b011 #
#50000000
b011 !
b00001000 "
b011 $
b00001000 %
#60000000
b100 #
#65000000
b100 !
b00010000 "
b100 $
b00010000 %
#75000000
b101 #
#80000000
b101 !
b00100000 "
b101 $
b00100000 %
#90000000
b110 #
#95000000
b110 !
b01000000 "
b110 $
b01000000 %
#105000000
b111 #
#110000000
b111 !
b10000000 "
b111 $
b10000000 %
#120000000
b000 #
