3/miselanea_ejemplos/ejemplo13/decoder3_8.vhd
library IEEE; 
use IEEE.STD_LOGIC_1164.all;

entity decoder3_8 is
  port(a: in STD_LOGIC_VECTOR(2 downto 0);
  y: out STD_LOGIC_VECTOR(7 downto 0));
end;

architecture synth of decoder3_8 is
begin
  process(all) 
  begin
    case a is
      when "000" => y <= "00000001";
      when "001" => y <= "00000010";
      when "010" => y <= "00000100";
      when "011" => y <= "00001000";
      when "100" => y <= "00010000";
      when "101" => y <= "00100000";
      when "110" => y <= "01000000";
      when "111" => y <= "10000000";
      when others => y <= "XXXXXXXX";
    end case;
  end process;
end;

3/miselanea_ejemplos/ejemplo13/decoder3_8_tb.vhd
library ieee;
use ieee.std_logic_1164.all;
use ieee.numeric_std.all;
use ieee.numeric_std_unsigned.all;

entity decoder3_8_tb is
end entity decoder3_8_tb;

architecture RTL of decoder3_8_tb is
	component decoder3_8
		port(
			a : in  STD_LOGIC_VECTOR(2 downto 0);
			y : out STD_LOGIC_VECTOR(7 downto 0)
		);
	end component decoder3_8;
	
	signal a : std_logic_vector(2 downto 0) := "000";
	signal y : std_logic_vector(7 downto 0);
	
	constant T : time := 10 ns;
	
begin
	
	DUT: decoder3_8
		port map(
			a => a,
			y => y
		);
		
	stimulus : process is
	begin
		wait for T;
		for i in 0 to 7 loop
			a <= a + "001";
			wait for T;
		end loop;
		wait;
		
	end process stimulus;
	

end architecture RTL;

3/miselanea_ejemplos/ejemplo13/decoder3_8_wf.vcd
$date
  Fri Mar 27 09:38:06 2020
$end
$version
  GHDL v0
$end
$timescale
  1 fs
$end
$scope module standard $end
$upscope $end
$scope module textio $end
$upscope $end
$scope module std_logic_1164 $end
$upscope $end
$scope module numeric_std $end
$upscope $end
$scope module numeric_std_unsigned $end
$upscope $end
$scope module decoder3_8_tb $end
$var reg 3 ! a[2:0] $end
$var reg 8 " y[7:0] $end
$scope module dut $end
$var reg 3 # a[2:0] $end
$var reg 8 $ y[7:0] $end
$upscope $end
$upscope $end
$enddefinitions $end
#0
b000 !
b00000001 "
b000 #
b00000001 $
#10000000
b001 !
b00000010 "
b001 #
b00000010 $
#20000000
b010 !
b00000100 "
b010 #
b00000100 $
#30000000
b011 !
b00001000 "
b011 #
b00001000 $
#40000000
b100 !
b00010000 "
b100 #
b00010000 $
#50000000
b101 !
b00100000 "
b101 #
b00100000 $
#60000000
b110 !
b01000000 "
b110 #
b01000000 $
#70000000
b111 !
b10000000 "
b111 #
b10000000 $
#80000000
b000 !
b00000001 "
b000 #
b00000001 $
