2/test_benchs/rca_test_bench/fulladder_dataflow.vhd
--------------------------------------------
-- Module Name: fulladder_dataflow
--------------------------------------------

library IEEE;
use IEEE.STD_LOGIC_1164.ALL;

Entity fulladder_dataflow Is
port(
		a  	 : in STD_LOGIC;
		b  	 : in STD_LOGIC;
		cin  : in STD_LOGIC;
		s 	 : out STD_LOGIC;
		cout : out STD_LOGIC
	);
end fulladder_dataflow;

Architecture behavior of fulladder_dataflow Is

begin
    process (a, b, cin) 
    begin
        s <= a xor b xor cin;
        cout <= (a and b) or (a and cin) or (b and cin);
	end process;
	
end behavior;

2/test_benchs/rca_test_bench/rca_dataflow.vhd
--------------------------------------------
-- Module Name: rca_dataflow
--------------------------------------------

library IEEE;
use IEEE.STD_LOGIC_1164.ALL;

Entity rca_dataflow Is
port(
		a  	 : in STD_LOGIC_VECTOR (3 downto 0);
		b  	 : in STD_LOGIC_VECTOR (3 downto 0);
		cin  : in STD_LOGIC;
		s 	 : out STD_LOGIC_VECTOR (3 downto 0);
		cout : out STD_LOGIC
	);
end rca_dataflow;

Architecture behavior of rca_dataflow Is
	Component fulladder_dataflow
	port (
		a  	 : in STD_LOGIC;
		b  	 : in STD_LOGIC;
		cin  : in STD_LOGIC;
		s 	 : out STD_LOGIC;
		cout : out STD_LOGIC
	);	
	End Component;

signal cout_i : STD_LOGIC_VECTOR (3 downto 0);

begin
	F0:  fulladder_dataflow PORT MAP (
			a => a(0),
			b => b(0),
			cin => cin,
			s => s(0),
			cout => cout_i(0)
		 );

	F1:  fulladder_dataflow PORT MAP (
			a => a(1),
			b => b(1),
			cin => cout_i(0),
			s => s(1),
			cout => cout_i(1)
		 );

	F2:  fulladder_dataflow PORT MAP (
			a => a(2),
			b => b(2),
			cin => cout_i(1),
			s => s(2),
			cout => cout_i(2)
		 );
		 
	F3:  fulladder_dataflow PORT MAP (
			a => a(3),
			b => b(3),
			cin => cout_i(2),
			s => s(3),
			cout => cout_i(3)
		 );		 
		 
	cout <= cout_i(3);

end behavior;

2/test_benchs/rca_test_bench/rca_dataflow_tb.vhd
--------------------------------------------
-- Module Name: fulladder_dataflow_tb
--------------------------------------------

library IEEE;
use IEEE.STD_LOGIC_1164.ALL;
use IEEE.NUMERIC_STD.ALL;
use STD.TEXTIO.ALL;

Entity rca_dataflow_tb Is
end rca_dataflow_tb;

Architecture behavior of rca_dataflow_tb Is
	Component rca_dataflow Is
	port(
			a  	 : in STD_LOGIC_VECTOR (3 downto 0);
			b  	 : in STD_LOGIC_VECTOR (3 downto 0);
			cin  : in STD_LOGIC;
			s 	 : out STD_LOGIC_VECTOR (3 downto 0);
			cout : out STD_LOGIC
		);
	End Component;
	
	Signal a_sig 	: STD_LOGIC_VECTOR (3 downto 0) := "0000";
	Signal b_sig 	: STD_LOGIC_VECTOR (3 downto 0) := "0000";
	Signal cin_sig      : STD_LOGIC := '0';
	

	Signal s_sig	: STD_LOGIC_VECTOR (3 downto 0);
	Signal cout_sig : STD_LOGIC;
	
begin
	DUT:  rca_dataflow PORT MAP (
		a    => a_sig,
		b    => b_sig,
		cin  => cin_sig,
		s    => s_sig,
		cout => cout_sig
		 );
		 
	process
	variable s : line; 
	variable suma_integer : integer;
	variable suma_unsigned : unsigned (3 downto 0);
	variable errors : boolean := false;


	begin
		for i in 0 to 15 loop
			for j in i to 15 loop
				for k in 0 to 1 loop
					a_sig <= std_logic_vector(to_unsigned(i,4));
					b_sig <= std_logic_vector(to_unsigned(i,4));
					if k = 1 then
						cin_sig <= '1';
					else
						cin_sig <= '0';												
					end if;
					wait for 20 ns;
					suma_unsigned := to_unsigned(i + j + k, 4);
					suma_integer := i + j + k;
					write(s, string'("a: ")); write(s, i);
					write(s, string'("; b: ")); write(s, j);
					write(s, string'("; cin: ")); write(s, k);
					writeline(output,s);
					-- Carry check
					if cout_sig = std_logic(suma_unsigned(3)) then
						write(s, string'("Carry Ok"));
						writeline(output,s);
					else
						write(s, string'("Error de Carry. Se esperaba "));
						write(s, k);
						writeline(output,s);
						errors := true;
					end if;
					-- Sum check
					if std_logic_vector(suma_unsigned((3) downto 0)) = s_sig then
						write(s, string'("Suma Ok"));
						writeline(output,s);
					else
						write(s, string'("Error de Suma. Se esperaba "));
						write(s, suma_integer);
						writeline(output,s);
						errors := true;
					end if;
					--if errors then exit; end if;
				end loop;
				--if errors then exit; end if;
		end loop;    
		--if errors then exit; end if;
	end loop;
	wait;
	end process;
end behavior;

2/test_benchs/rca_test_bench/full_adder_dataflow_tb_results.vcd
$date
  Thu Jul 25 19:27:32 2019
$end
$version
  GHDL v0
$end
$timescale
  1 fs
$end
$scope module standard $end
$upscope $end
$scope module std_logic_1164 $end
$upscope $end
$scope module numeric_std $end
$upscope $end
$scope module textio $end
$upscope $end
$scope module rca_dataflow_tb $end
$var reg 4 ! a_sig[3:0] $end
$var reg 4 " b_sig[3:0] $end
$var reg 1 # cin_sig $end
$var reg 4 $ s_sig[3:0] $end
$var reg 1 % cout_sig $end
$scope module dut $end
$var reg 4 & a[3:0] $end
$var reg 4 ' b[3:0] $end
$var reg 1 ( cin $end
$var reg 4 ) s[3:0] $end
$var reg 1 * cout $end
$var reg 4 + cout_i[3:0] $end
$scope module f0 $end
$var reg 1 , a $end
$var reg 1 - b $end
$var reg 1 . cin $end
$var reg 1 / s $end
$var reg 1 0 cout $end
$upscope $end
$scope module f1 $end
$var reg 1 1 a $end
$var reg 1 2 b $end
$var reg 1 3 cin $end
$var reg 1 4 s $end
$var reg 1 5 cout $end
$upscope $end
$scope module f2 $end
$var reg 1 6 a $end
$var reg 1 7 b $end
$var reg 1 8 cin $end
$var reg 1 9 s $end
$var reg 1 : cout $end
$upscope $end
$scope module f3 $end
$var reg 1 ; a $end
$var reg 1 < b $end
$var reg 1 = cin $end
$var reg 1 > s $end
$var reg 1 ? cout $end
$upscope $end
$upscope $end
$upscope $end
$enddefinitions $end
#0
b0000 !
b0000 "
0#
b0000 $
0%
b0000 &
b0000 '
0(
b0000 )
0*
b0000 +
0,
0-
0.
0/
00
01
02
03
04
05
06
07
08
09
0:
0;
0<
0=
0>
0?
#20000000
1#
b0001 $
1(
b0001 )
1.
1/
#40000000
0#
b0000 $
0(
b0000 )
0.
0/
#60000000
1#
b0001 $
1(
b0001 )
1.
1/
#80000000
0#
b0000 $
0(
b0000 )
0.
0/
#100000000
1#
b0001 $
1(
b0001 )
1.
1/
#120000000
0#
b0000 $
0(
b0000 )
0.
0/
#140000000
1#
b0001 $
1(
b0001 )
1.
1/
#160000000
0#
b0000 $
0(
b0000 )
0.
0/
#180000000
1#
b0001 $
1(
b0001 )
1.
1/
#200000000
0#
b0000 $
0(
b0000 )
0.
0/
#220000000
1#
b0001 $
1(
b0001 )
1.
1/
#240000000
0#
b0000 $
0(
b0000 )
0.
0/
#260000000
1#
b0001 $
1(
b0001 )
1.
1/
#280000000
0#
b0000 $
0(
b0000 )
0.
0/
#300000000
1#
b0001 $
1(
b0001 )
1.
1/
#320000000
0#
b0000 $
0(
b0000 )
0.
0/
#340000000
1#
b0001 $
1(
b0001 )
1.
1/
#360000000
0#
b0000 $
0(
b0000 )
0.
0/
#380000000
1#
b0001 $
1(
b0001 )
1.
1/
#400000000
0#
b0000 $
0(
b0000 )
0.
0/
#420000000
1#
b0001 $
1(
b0001 )
1.
1/
#440000000
0#
b0000 $
0(
b0000 )
0.
0/
#460000000
1#
b0001 $
1(
b0001 )
1.
1/
#480000000
0#
b0000 $
0(
b0000 )
0.
0/
#500000000
1#
b0001 $
1(
b0001 )
1.
1/
#520000000
0#
b0000 $
0(
b0000 )
0.
0/
#540000000
1#
b0001 $
1(
b0001 )
1.
1/
#560000000
0#
b0000 $
0(
b0000 )
0.
0/
#580000000
1#
b0001 $
1(
b0001 )
1.
1/
#600000000
0#
b0000 $
0(
b0000 )
0.
0/
#620000000
1#
b0001 $
1(
b0001 )
1.
1/
#640000000
b0001 !
b0001 "
0#
b0010 $
b0001 &
b0001 '
0(
b0010 )
b0001 +
1,
1-
0.
0/
10
13
14
#660000000
1#
b0011 $
1(
b0011 )
1.
1/
#680000000
0#
b0010 $
0(
b0010 )
0.
0/
#700000000
1#
b0011 $
1(
b0011 )
1.
1/
#720000000
0#
b0010 $
0(
b0010 )
0.
0/
#740000000
1#
b0011 $
1(
b0011 )
1.
1/
#760000000
0#
b0010 $
0(
b0010 )
0.
0/
#780000000
1#
b0011 $
1(
b0011 )
1.
1/
#800000000
0#
b0010 $
0(
b0010 )
0.
0/
#820000000
1#
b0011 $
1(
b0011 )
1.
1/
#840000000
0#
b0010 $
0(
b0010 )
0.
0/
#860000000
1#
b0011 $
1(
b0011 )
1.
1/
#880000000
0#
b0010 $
0(
b0010 )
0.
0/
#900000000
1#
b0011 $
1(
b0011 )
1.
1/
#920000000
0#
b0010 $
0(
b0010 )
0.
0/
#940000000
1#
b0011 $
1(
b0011 )
1.
1/
#960000000
0#
b0010 $
0(
b0010 )
0.
0/
#980000000
1#
b0011 $
1(
b0011 )
1.
1/
#1000000000
0#
b0010 $
0(
b0010 )
0.
0/
#1020000000
1#
b0011 $
1(
b0011 )
1.
1/
#1040000000
0#
b0010 $
0(
b0010 )
0.
0/
#1060000000
1#
b0011 $
1(
b0011 )
1.
1/
#1080000000
0#
b0010 $
0(
b0010 )
0.
0/
#1100000000
1#
b0011 $
1(
b0011 )
1.
1/
#1120000000
0#
b0010 $
0(
b0010 )
0.
0/
#1140000000
1#
b0011 $
1(
b0011 )
1.
1/
#1160000000
0#
b0010 $
0(
b0010 )
0.
0/
#1180000000
1#
b0011 $
1(
b0011 )
1.
1/
#1200000000
0#
b0010 $
0(
b0010 )
0.
0/
#1220000000
1#
b0011 $
1(
b0011 )
1.
1/
#1240000000
b0010 !
b0010 "
0#
b0100 $
b0010 &
b0010 '
0(
b0100 )
b0010 +
0,
0-
0.
0/
00
11
12
03
04
15
18
19
#1260000000
1#
b0101 $
1(
b0101 )
1.
1/
#1280000000
0#
b0100 $
0(
b0100 )
0.
0/
#1300000000
1#
b0101 $
1(
b0101 )
1.
1/
#1320000000
0#
b0100 $
0(
b0100 )
0.
0/
#1340000000
1#
b0101 $
1(
b0101 )
1.
1/
#1360000000
0#
b0100 $
0(
b0100 )
0.
0/
#1380000000
1#
b0101 $
1(
b0101 )
1.
1/
#1400000000
0#
b0100 $
0(
b0100 )
0.
0/
#1420000000
1#
b0101 $
1(
b0101 )
1.
1/
#1440000000
0#
b0100 $
0(
b0100 )
0.
0/
#1460000000
1#
b0101 $
1(
b0101 )
1.
1/
#1480000000
0#
b0100 $
0(
b0100 )
0.
0/
#1500000000
1#
b0101 $
1(
b0101 )
1.
1/
#1520000000
0#
b0100 $
0(
b0100 )
0.
0/
#1540000000
1#
b0101 $
1(
b0101 )
1.
1/
#1560000000
0#
b0100 $
0(
b0100 )
0.
0/
#1580000000
1#
b0101 $
1(
b0101 )
1.
1/
#1600000000
0#
b0100 $
0(
b0100 )
0.
0/
#1620000000
1#
b0101 $
1(
b0101 )
1.
1/
#1640000000
0#
b0100 $
0(
b0100 )
0.
0/
#1660000000
1#
b0101 $
1(
b0101 )
1.
1/
#1680000000
0#
b0100 $
0(
b0100 )
0.
0/
#1700000000
1#
b0101 $
1(
b0101 )
1.
1/
#1720000000
0#
b0100 $
0(
b0100 )
0.
0/
#1740000000
1#
b0101 $
1(
b0101 )
1.
1/
#1760000000
0#
b0100 $
0(
b0100 )
0.
0/
#1780000000
1#
b0101 $
1(
b0101 )
1.
1/
#1800000000
b0011 !
b0011 "
0#
b0110 $
b0011 &
b0011 '
0(
b0110 )
b0011 +
1,
1-
0.
0/
10
13
14
#1820000000
1#
b0111 $
1(
b0111 )
1.
1/
#1840000000
0#
b0110 $
0(
b0110 )
0.
0/
#1860000000
1#
b0111 $
1(
b0111 )
1.
1/
#1880000000
0#
b0110 $
0(
b0110 )
0.
0/
#1900000000
1#
b0111 $
1(
b0111 )
1.
1/
#1920000000
0#
b0110 $
0(
b0110 )
0.
0/
#1940000000
1#
b0111 $
1(
b0111 )
1.
1/
#1960000000
0#
b0110 $
0(
b0110 )
0.
0/
#1980000000
1#
b0111 $
1(
b0111 )
1.
1/
#2000000000
0#
b0110 $
0(
b0110 )
0.
0/
#2020000000
1#
b0111 $
1(
b0111 )
1.
1/
#2040000000
0#
b0110 $
0(
b0110 )
0.
0/
#2060000000
1#
b0111 $
1(
b0111 )
1.
1/
#2080000000
0#
b0110 $
0(
b0110 )
0.
0/
#2100000000
1#
b0111 $
1(
b0111 )
1.
1/
#2120000000
0#
b0110 $
0(
b0110 )
0.
0/
#2140000000
1#
b0111 $
1(
b0111 )
1.
1/
#2160000000
0#
b0110 $
0(
b0110 )
0.
0/
#2180000000
1#
b0111 $
1(
b0111 )
1.
1/
#2200000000
0#
b0110 $
0(
b0110 )
0.
0/
#2220000000
1#
b0111 $
1(
b0111 )
1.
1/
#2240000000
0#
b0110 $
0(
b0110 )
0.
0/
#2260000000
1#
b0111 $
1(
b0111 )
1.
1/
#2280000000
0#
b0110 $
0(
b0110 )
0.
0/
#2300000000
1#
b0111 $
1(
b0111 )
1.
1/
#2320000000
b0100 !
b0100 "
0#
b1000 $
b0100 &
b0100 '
0(
b1000 )
b0100 +
0,
0-
0.
0/
00
01
02
03
04
05
16
17
08
09
1:
1=
1>
#2340000000
1#
b1001 $
1(
b1001 )
1.
1/
#2360000000
0#
b1000 $
0(
b1000 )
0.
0/
#2380000000
1#
b1001 $
1(
b1001 )
1.
1/
#2400000000
0#
b1000 $
0(
b1000 )
0.
0/
#2420000000
1#
b1001 $
1(
b1001 )
1.
1/
#2440000000
0#
b1000 $
0(
b1000 )
0.
0/
#2460000000
1#
b1001 $
1(
b1001 )
1.
1/
#2480000000
0#
b1000 $
0(
b1000 )
0.
0/
#2500000000
1#
b1001 $
1(
b1001 )
1.
1/
#2520000000
0#
b1000 $
0(
b1000 )
0.
0/
#2540000000
1#
b1001 $
1(
b1001 )
1.
1/
#2560000000
0#
b1000 $
0(
b1000 )
0.
0/
#2580000000
1#
b1001 $
1(
b1001 )
1.
1/
#2600000000
0#
b1000 $
0(
b1000 )
0.
0/
#2620000000
1#
b1001 $
1(
b1001 )
1.
1/
#2640000000
0#
b1000 $
0(
b1000 )
0.
0/
#2660000000
1#
b1001 $
1(
b1001 )
1.
1/
#2680000000
0#
b1000 $
0(
b1000 )
0.
0/
#2700000000
1#
b1001 $
1(
b1001 )
1.
1/
#2720000000
0#
b1000 $
0(
b1000 )
0.
0/
#2740000000
1#
b1001 $
1(
b1001 )
1.
1/
#2760000000
0#
b1000 $
0(
b1000 )
0.
0/
#2780000000
1#
b1001 $
1(
b1001 )
1.
1/
#2800000000
b0101 !
b0101 "
0#
b1010 $
b0101 &
b0101 '
0(
b1010 )
b0101 +
1,
1-
0.
0/
10
13
14
#2820000000
1#
b1011 $
1(
b1011 )
1.
1/
#2840000000
0#
b1010 $
0(
b1010 )
0.
0/
#2860000000
1#
b1011 $
1(
b1011 )
1.
1/
#2880000000
0#
b1010 $
0(
b1010 )
0.
0/
#2900000000
1#
b1011 $
1(
b1011 )
1.
1/
#2920000000
0#
b1010 $
0(
b1010 )
0.
0/
#2940000000
1#
b1011 $
1(
b1011 )
1.
1/
#2960000000
0#
b1010 $
0(
b1010 )
0.
0/
#2980000000
1#
b1011 $
1(
b1011 )
1.
1/
#3000000000
0#
b1010 $
0(
b1010 )
0.
0/
#3020000000
1#
b1011 $
1(
b1011 )
1.
1/
#3040000000
0#
b1010 $
0(
b1010 )
0.
0/
#3060000000
1#
b1011 $
1(
b1011 )
1.
1/
#3080000000
0#
b1010 $
0(
b1010 )
0.
0/
#3100000000
1#
b1011 $
1(
b1011 )
1.
1/
#3120000000
0#
b1010 $
0(
b1010 )
0.
0/
#3140000000
1#
b1011 $
1(
b1011 )
1.
1/
#3160000000
0#
b1010 $
0(
b1010 )
0.
0/
#3180000000
1#
b1011 $
1(
b1011 )
1.
1/
#3200000000
0#
b1010 $
0(
b1010 )
0.
0/
#3220000000
1#
b1011 $
1(
b1011 )
1.
1/
#3240000000
b0110 !
b0110 "
0#
b1100 $
b0110 &
b0110 '
0(
b1100 )
b0110 +
0,
0-
0.
0/
00
11
12
03
04
15
18
19
#3260000000
1#
b1101 $
1(
b1101 )
1.
1/
#3280000000
0#
b1100 $
0(
b1100 )
0.
0/
#3300000000
1#
b1101 $
1(
b1101 )
1.
1/
#3320000000
0#
b1100 $
0(
b1100 )
0.
0/
#3340000000
1#
b1101 $
1(
b1101 )
1.
1/
#3360000000
0#
b1100 $
0(
b1100 )
0.
0/
#3380000000
1#
b1101 $
1(
b1101 )
1.
1/
#3400000000
0#
b1100 $
0(
b1100 )
0.
0/
#3420000000
1#
b1101 $
1(
b1101 )
1.
1/
#3440000000
0#
b1100 $
0(
b1100 )
0.
0/
#3460000000
1#
b1101 $
1(
b1101 )
1.
1/
#3480000000
0#
b1100 $
0(
b1100 )
0.
0/
#3500000000
1#
b1101 $
1(
b1101 )
1.
1/
#3520000000
0#
b1100 $
0(
b1100 )
0.
0/
#3540000000
1#
b1101 $
1(
b1101 )
1.
1/
#3560000000
0#
b1100 $
0(
b1100 )
0.
0/
#3580000000
1#
b1101 $
1(
b1101 )
1.
1/
#3600000000
0#
b1100 $
0(
b1100 )
0.
0/
#3620000000
1#
b1101 $
1(
b1101 )
1.
1/
#3640000000
b0111 !
b0111 "
0#
b1110 $
b0111 &
b0111 '
0(
b1110 )
b0111 +
1,
1-
0.
0/
10
13
14
#3660000000
1#
b1111 $
1(
b1111 )
1.
1/
#3680000000
0#
b1110 $
0(
b1110 )
0.
0/
#3700000000
1#
b1111 $
1(
b1111 )
1.
1/
#3720000000
0#
b1110 $
0(
b1110 )
0.
0/
#3740000000
1#
b1111 $
1(
b1111 )
1.
1/
#3760000000
0#
b1110 $
0(
b1110 )
0.
0/
#3780000000
1#
b1111 $
1(
b1111 )
1.
1/
#3800000000
0#
b1110 $
0(
b1110 )
0.
0/
#3820000000
1#
b1111 $
1(
b1111 )
1.
1/
#3840000000
0#
b1110 $
0(
b1110 )
0.
0/
#3860000000
1#
b1111 $
1(
b1111 )
1.
1/
#3880000000
0#
b1110 $
0(
b1110 )
0.
0/
#3900000000
1#
b1111 $
1(
b1111 )
1.
1/
#3920000000
0#
b1110 $
0(
b1110 )
0.
0/
#3940000000
1#
b1111 $
1(
b1111 )
1.
1/
#3960000000
0#
b1110 $
0(
b1110 )
0.
0/
#3980000000
1#
b1111 $
1(
b1111 )
1.
1/
#4000000000
b1000 !
b1000 "
0#
b0000 $
1%
b1000 &
b1000 '
0(
b0000 )
1*
b1000 +
0,
0-
0.
0/
00
01
02
03
04
05
06
07
08
09
0:
1;
1<
0=
0>
1?
#4020000000
1#
b0001 $
1(
b0001 )
1.
1/
#4040000000
0#
b0000 $
0(
b0000 )
0.
0/
#4060000000
1#
b0001 $
1(
b0001 )
1.
1/
#4080000000
0#
b0000 $
0(
b0000 )
0.
0/
#4100000000
1#
b0001 $
1(
b0001 )
1.
1/
#4120000000
0#
b0000 $
0(
b0000 )
0.
0/
#4140000000
1#
b0001 $
1(
b0001 )
1.
1/
#4160000000
0#
b0000 $
0(
b0000 )
0.
0/
#4180000000
1#
b0001 $
1(
b0001 )
1.
1/
#4200000000
0#
b0000 $
0(
b0000 )
0.
0/
#4220000000
1#
b0001 $
1(
b0001 )
1.
1/
#4240000000
0#
b0000 $
0(
b0000 )
0.
0/
#4260000000
1#
b0001 $
1(
b0001 )
1.
1/
#4280000000
0#
b0000 $
0(
b0000 )
0.
0/
#4300000000
1#
b0001 $
1(
b0001 )
1.
1/
#4320000000
b1001 !
b1001 "
0#
b0010 $
b1001 &
b1001 '
0(
b0010 )
b1001 +
1,
1-
0.
0/
10
13
14
#4340000000
1#
b0011 $
1(
b0011 )
1.
1/
#4360000000
0#
b0010 $
0(
b0010 )
0.
0/
#4380000000
1#
b0011 $
1(
b0011 )
1.
1/
#4400000000
0#
b0010 $
0(
b0010 )
0.
0/
#4420000000
1#
b0011 $
1(
b0011 )
1.
1/
#4440000000
0#
b0010 $
0(
b0010 )
0.
0/
#4460000000
1#
b0011 $
1(
b0011 )
1.
1/
#4480000000
0#
b0010 $
0(
b0010 )
0.
0/
#4500000000
1#
b0011 $
1(
b0011 )
1.
1/
#4520000000
0#
b0010 $
0(
b0010 )
0.
0/
#4540000000
1#
b0011 $
1(
b0011 )
1.
1/
#4560000000
0#
b0010 $
0(
b0010 )
0.
0/
#4580000000
1#
b0011 $
1(
b0011 )
1.
1/
#4600000000
b1010 !
b1010 "
0#
b0100 $
b1010 &
b1010 '
0(
b0100 )
b1010 +
0,
0-
0.
0/
00
11
12
03
04
15
18
19
#4620000000
1#
b0101 $
1(
b0101 )
1.
1/
#4640000000
0#
b0100 $
0(
b0100 )
0.
0/
#4660000000
1#
b0101 $
1(
b0101 )
1.
1/
#4680000000
0#
b0100 $
0(
b0100 )
0.
0/
#4700000000
1#
b0101 $
1(
b0101 )
1.
1/
#4720000000
0#
b0100 $
0(
b0100 )
0.
0/
#4740000000
1#
b0101 $
1(
b0101 )
1.
1/
#4760000000
0#
b0100 $
0(
b0100 )
0.
0/
#4780000000
1#
b0101 $
1(
b0101 )
1.
1/
#4800000000
0#
b0100 $
0(
b0100 )
0.
0/
#4820000000
1#
b0101 $
1(
b0101 )
1.
1/
#4840000000
b1011 !
b1011 "
0#
b0110 $
b1011 &
b1011 '
0(
b0110 )
b1011 +
1,
1-
0.
0/
10
13
14
#4860000000
1#
b0111 $
1(
b0111 )
1.
1/
#4880000000
0#
b0110 $
0(
b0110 )
0.
0/
#4900000000
1#
b0111 $
1(
b0111 )
1.
1/
#4920000000
0#
b0110 $
0(
b0110 )
0.
0/
#4940000000
1#
b0111 $
1(
b0111 )
1.
1/
#4960000000
0#
b0110 $
0(
b0110 )
0.
0/
#4980000000
1#
b0111 $
1(
b0111 )
1.
1/
#5000000000
0#
b0110 $
0(
b0110 )
0.
0/
#5020000000
1#
b0111 $
1(
b0111 )
1.
1/
#5040000000
b1100 !
b1100 "
0#
b1000 $
b1100 &
b1100 '
0(
b1000 )
b1100 +
0,
0-
0.
0/
00
01
02
03
04
05
16
17
08
09
1:
1=
1>
#5060000000
1#
b1001 $
1(
b1001 )
1.
1/
#5080000000
0#
b1000 $
0(
b1000 )
0.
0/
#5100000000
1#
b1001 $
1(
b1001 )
1.
1/
#5120000000
0#
b1000 $
0(
b1000 )
0.
0/
#5140000000
1#
b1001 $
1(
b1001 )
1.
1/
#5160000000
0#
b1000 $
0(
b1000 )
0.
0/
#5180000000
1#
b1001 $
1(
b1001 )
1.
1/
#5200000000
b1101 !
b1101 "
0#
b1010 $
b1101 &
b1101 '
0(
b1010 )
b1101 +
1,
1-
0.
0/
10
13
14
#5220000000
1#
b1011 $
1(
b1011 )
1.
1/
#5240000000
0#
b1010 $
0(
b1010 )
0.
0/
#5260000000
1#
b1011 $
1(
b1011 )
1.
1/
#5280000000
0#
b1010 $
0(
b1010 )
0.
0/
#5300000000
1#
b1011 $
1(
b1011 )
1.
1/
#5320000000
b1110 !
b1110 "
0#
b1100 $
b1110 &
b1110 '
0(
b1100 )
b1110 +
0,
0-
0.
0/
00
11
12
03
04
15
18
19
#5340000000
1#
b1101 $
1(
b1101 )
1.
1/
#5360000000
0#
b1100 $
0(
b1100 )
0.
0/
#5380000000
1#
b1101 $
1(
b1101 )
1.
1/
#5400000000
b1111 !
b1111 "
0#
b1110 $
b1111 &
b1111 '
0(
b1110 )
b1111 +
1,
1-
0.
0/
10
13
14
#5420000000
1#
b1111 $
1(
b1111 )
1.
1/
