2/test_benchs/rca_test_bench/fulladder_dataflow.vhd
--------------------------------------------
-- Module Name: fulladder_dataflow
--------------------------------------------

library IEEE;
use IEEE.STD_LOGIC_1164.ALL;

Entity fulladder_dataflow Is
port(
		a  	 : in STD_LOGIC;
		b  	 : in STD_LOGIC;
		cin  : in STD_LOGIC;
		s 	 : out STD_LOGIC;
		cout : out STD_LOGIC
	);
end fulladder_dataflow;

Architecture behavior of fulladder_dataflow Is

begin
    process (a, b, cin) 
    begin
        s <= a xor b xor cin;
        cout <= (a and b) or (a and cin) or (b and cin);
	end process;
	
end behavior;

2/test_benchs/rca_test_bench/rca_dataflow.vhd
--------------------------------------------
-- Module Name: rca_dataflow
--------------------------------------------

library IEEE;
use IEEE.STD_LOGIC_1164.ALL;

Entity rca_dataflow Is
port(
		a  	 : in STD_LOGIC_VECTOR (3 downto 0);
		b  	 : in STD_LOGIC_VECTOR (3 downto 0);
		cin  : in STD_LOGIC;
		s 	 : out STD_LOGIC_VECTOR (3 downto 0);
		cout : out STD_LOGIC
	);
end rca_dataflow;

Architecture behavior of rca_dataflow Is
	Component fulladder_dataflow
	port (
		a  	 : in STD_LOGIC;
		b  	 : in STD_LOGIC;
		cin  : in STD_LOGIC;
		s 	 : out STD_LOGIC;
		cout : out STD_LOGIC
	);	
	End Component;

signal cout_i : STD_LOGIC_VECTOR (3 downto 0);

begin
	F0:  fulladder_dataflow PORT MAP (
			a => a(0),
			b => b(0),
			cin => cin,
			s => s(0),
			cout => cout_i(0)
		 );

	F1:  fulladder_dataflow PORT MAP (
			a => a(1),
			b => b(1),
			cin => cout_i(0),
			s => s(1),
			cout => cout_i(1)
		 );

	F2:  fulladder_dataflow PORT MAP (
			a => a(2),
			b => b(2),
			cin => cout_i(1),
			s => s(2),
			cout => cout_i(2)
		 );
		 
	F3:  fulladder_dataflow PORT MAP (
			a => a(3),
			b => b(3),
			cin => cout_i(2),
			s => s(3),
			cout => cout_i(3)
		 );		 
		 
	cout <= cout_i(3);

end behavior;

2/test_benchs/rca_test_bench/rca_dataflow_tb1.vhd
--------------------------------------------
-- Module Name: fulladder_dataflow_tb
--------------------------------------------

library IEEE;
use IEEE.STD_LOGIC_1164.ALL;
use IEEE.NUMERIC_STD.ALL;
use STD.TEXTIO.ALL;

Entity rca_dataflow_tb Is
end rca_dataflow_tb;

Architecture behavior of rca_dataflow_tb Is
	Component rca_dataflow Is
	port(
			a  	 : in STD_LOGIC_VECTOR (3 downto 0);
			b  	 : in STD_LOGIC_VECTOR (3 downto 0);
			cin  : in STD_LOGIC;
			s 	 : out STD_LOGIC_VECTOR (3 downto 0);
			cout : out STD_LOGIC
		);
	End Component;
	
	Signal a_sig 	: STD_LOGIC_VECTOR (3 downto 0) := "0000";
	Signal b_sig 	: STD_LOGIC_VECTOR (3 downto 0) := "0000";
	Signal cin_sig      : STD_LOGIC := '0';
	

	Signal s_sig	: STD_LOGIC_VECTOR (3 downto 0);
	Signal cout_sig : STD_LOGIC;
	
begin
	DUT:  rca_dataflow PORT MAP (
		a    => a_sig,
		b    => b_sig,
		cin  => cin_sig,
		s    => s_sig,
		cout => cout_sig
		 );
		 
	process

	begin
		wait for 10 ns;
		a_sig <= "0000";
		b_sig <= "0000";
		cin_sig <= '0';
		wait for 10 ns;
		a_sig <= "0000";
		b_sig <= "0000";
		cin_sig <= '1';
		wait for 10 ns;
		a_sig <= "0100";
		b_sig <= "0001";
		cin_sig <= '1';
		wait for 10 ns;
		a_sig <= "0100";
		b_sig <= "0111";
		cin_sig <= '1';
		wait for 10 ns;
		a_sig <= "1111";
		b_sig <= "0000";
		cin_sig <= '1';
		wait for 10 ns;
		a_sig <= "1111";
		b_sig <= "0001";
		cin_sig <= '1';
		wait for 10 ns;
		a_sig <= "1111";
		b_sig <= "1111";
		cin_sig <= '0';
		wait for 10 ns;
		a_sig <= "1000";
		b_sig <= "1000";
		cin_sig <= '0';
		wait for 10 ns;
		a_sig <= "1000";
		b_sig <= "1000";
		cin_sig <= '1';
	wait;
	end process;
end behavior;

2/test_benchs/rca_test_bench/full_adder_dataflow_tb_results.vcd
$date
  Fri Jul 26 14:05:52 2019
$end
$version
  GHDL v0
$end
$timescale
  1 fs
$end
$scope module standard $end
$upscope $end
$scope module std_logic_1164 $end
$upscope $end
$scope module numeric_std $end
$upscope $end
$scope module textio $end
$upscope $end
$scope module rca_dataflow_tb $end
$var reg 4 ! a_sig[3:0] $end
$var reg 4 " b_sig[3:0] $end
$var reg 1 # cin_sig $end
$var reg 4 $ s_sig[3:0] $end
$var reg 1 % cout_sig $end
$scope module dut $end
$var reg 4 & a[3:0] $end
$var reg 4 ' b[3:0] $end
$var reg 1 ( cin $end
$var reg 4 ) s[3:0] $end
$var reg 1 * cout $end
$var reg 4 + cout_i[3:0] $end
$scope module f0 $end
$var reg 1 , a $end
$var reg 1 - b $end
$var reg 1 . cin $end
$var reg 1 / s $end
$var reg 1 0 cout $end
$upscope $end
$scope module f1 $end
$var reg 1 1 a $end
$var reg 1 2 b $end
$var reg 1 3 cin $end
$var reg 1 4 s $end
$var reg 1 5 cout $end
$upscope $end
$scope module f2 $end
$var reg 1 6 a $end
$var reg 1 7 b $end
$var reg 1 8 cin $end
$var reg 1 9 s $end
$var reg 1 : cout $end
$upscope $end
$scope module f3 $end
$var reg 1 ; a $end
$var reg 1 < b $end
$var reg 1 = cin $end
$var reg 1 > s $end
$var reg 1 ? cout $end
$upscope $end
$upscope $end
$upscope $end
$enddefinitions $end
#0
b0000 !
b0000 "
0#
b0000 $
0%
b0000 &
b0000 '
0(
b0000 )
0*
b0000 +
0,
0-
0.
0/
00
01
02
03
04
05
06
07
08
09
0:
0;
0<
0=
0>
0?
#10000000
#20000000
1#
b0001 $
1(
b0001 )
1.
1/
#30000000
b0100 !
b0001 "
b0110 $
b0100 &
b0001 '
b0110 )
b0001 +
1-
0/
10
13
14
16
19
#40000000
b0111 "
b1100 $
b0111 '
b1100 )
b0111 +
12
04
15
17
18
19
1:
1=
1>
#50000000
b1111 !
b0000 "
b0000 $
1%
b1111 &
b0000 '
b0000 )
1*
b1111 +
1,
0-
11
02
07
09
1;
0>
1?
#60000000
b0001 "
b0001 $
b0001 '
b0001 )
1-
1/
#70000000
b1111 "
0#
b1110 $
b1111 '
0(
b1110 )
0.
0/
12
14
17
19
1<
1>
#80000000
b1000 !
b1000 "
b0000 $
b1000 &
b1000 '
b0000 )
b1000 +
0,
0-
00
01
02
03
04
05
06
07
08
09
0:
0=
0>
#90000000
1#
b0001 $
1(
b0001 )
1.
1/
