3/miselanea_ejemplos/ejemplo8/example.vhd

library IEEE;
use IEEE.STD_LOGIC_1164.all;

entity example is
	port(a, b, c : in  STD_LOGIC;
	     y       : out STD_LOGIC);
end;

architecture synth of example is
	signal ab, bb, cb, n1, n2, n3 : STD_LOGIC;
begin
	ab <= not a after 1 ns;
	bb <= not b after 1 ns;
	cb <= not c after 1 ns;
	n1 <= ab and bb and cb after 2 ns;
	n2 <= a and bb and cb after 2 ns;
	n3 <= a and bb and c after 2 ns;
	y  <= n1 or n2 or n3 after 4 ns;
end;

3/miselanea_ejemplos/ejemplo8/example_tb.vhd
library ieee;
use ieee.std_logic_1164.all;
use ieee.numeric_std.all;

entity example_tb is
end entity example_tb;

architecture RTL of example_tb is
	component example
		port(
			a, b, c : in  STD_LOGIC;
			y       : out STD_LOGIC
		);
	end component example;
	
	signal a, b, c : std_logic := '0';
	signal y : std_logic;
	
	constant T : time := 15 ns;
begin
	DUT:example
		port map(
			a => a,
			b => b,
			c => c,
			y => y
		);
		
	stimulus : process is
	begin
		wait for T;
		a <= '1';
		wait for T;
		b <= '1';		
		wait for T;
		c <= '1';
		wait for T;
		a <= '0';
		c <= '0';		
		wait for T;
		a <= '1';
		b <= '0';
		c <= '1';
		wait for T;
		wait;		
	end process stimulus;
end architecture RTL;

3/miselanea_ejemplos/ejemplo8/example_wf.vcd
$date
  Thu Mar 26 23:28:30 2020
$end
$version
  GHDL v0
$end
$timescale
  1 fs
$end
$scope module standard $end
$upscope $end
$scope module std_logic_1164 $end
$upscope $end
$scope module numeric_std $end
$upscope $end
$scope module example_tb $end
$var reg 1 ! a $end
$var reg 1 " b $end
$var reg 1 # c $end
$var reg 1 $ y $end
$scope module dut $end
$var reg 1 % a $end
$var reg 1 & b $end
$var reg 1 ' c $end
$var reg 1 ( y $end
$var reg 1 ) ab $end
$var reg 1 * bb $end
$var reg 1 + cb $end
$var reg 1 , n1 $end
$var reg 1 - n2 $end
$var reg 1 . n3 $end
$upscope $end
$upscope $end
$enddefinitions $end
#0
0!
0"
0#
U$
0%
0&
0'
U(
U)
U*
U+
U,
U-
U.
#1000000
1)
1*
1+
#2000000
0-
0.
#3000000
1,
#7000000
1$
1(
#15000000
1!
1%
#16000000
0)
#17000000
1-
#18000000
0,
#21000000
1(
#22000000
1(
#30000000
1"
1&
#31000000
0*
#33000000
0-
#37000000
0$
0(
#45000000
1#
1'
#46000000
0+
#47000000
#48000000
#60000000
0!
0#
0%
0'
#61000000
1)
1+
#62000000
#63000000
#75000000
1!
0"
1#
1%
0&
1'
#76000000
0)
1*
0+
#77000000
#78000000
1.
#82000000
1$
1(
