3/miselanea_ejemplos/ejemplo16/multiplier.vhd

-- 4.33(a): unsigned multiplier
library IEEE;
use IEEE.STD_LOGIC_1164.all;
use IEEE.NUMERIC_STD_UNSIGNED.all;

entity multiplier is
	port(a, b : in  STD_LOGIC_VECTOR(3 downto 0);
	     y    : out STD_LOGIC_VECTOR(7 downto 0));
end;

architecture synth of multiplier is
begin
	y <= a * b;
end;

3/miselanea_ejemplos/ejemplo16/multiplier_tb.vhd
library ieee;
use ieee.std_logic_1164.all;
use ieee.numeric_std.all;
use ieee.numeric_std_unsigned.all;

entity multiplier_tb is
end entity multiplier_tb;

architecture RTL of multiplier_tb is
	component multiplier
		port(
			a, b : in  STD_LOGIC_VECTOR(3 downto 0);
			y    : out STD_LOGIC_VECTOR(7 downto 0)
		);
	end component multiplier;

	signal a, b : std_logic_vector(3 downto 0) := "0000";
	signal y    : std_logic_vector(7 downto 0);

	constant T : time := 10 ns;
begin
	DUT : multiplier
		port map(
			a => a,
			b => b,
			y => y
		);

	stimulus : process is
	begin
		for i in 0 to 15 loop
			for j in 0 to 15 loop				
				wait for T;
				a <= a + '1';
			end loop;
			b <= b + '1';
			a <= "0000";
		end loop;
		wait;
	end process stimulus;

end architecture RTL;

3/miselanea_ejemplos/ejemplo16/multiplier_wf.vcd
$date
  Fri Mar 27 10:23:44 2020
$end
$version
  GHDL v0
$end
$timescale
  1 fs
$end
$scope module standard $end
$upscope $end
$scope module textio $end
$upscope $end
$scope module std_logic_1164 $end
$upscope $end
$scope module numeric_std $end
$upscope $end
$scope module numeric_std_unsigned $end
$upscope $end
$scope module multiplier_tb $end
$var reg 4 ! a[3:0] $end
$var reg 4 " b[3:0] $end
$var reg 8 # y[7:0] $end
$scope module dut $end
$var reg 4 $ a[3:0] $end
$var reg 4 % b[3:0] $end
$var reg 8 & y[7:0] $end
$upscope $end
$upscope $end
$enddefinitions $end
#0
b0000 !
b0000 "
b00000000 #
b0000 $
b0000 %
b00000000 &
#10000000
b0001 !
b0001 $
#20000000
b0010 !
b0010 $
#30000000
b0011 !
b0011 $
#40000000
b0100 !
b0100 $
#50000000
b0101 !
b0101 $
#60000000
b0110 !
b0110 $
#70000000
b0111 !
b0111 $
#80000000
b1000 !
b1000 $
#90000000
b1001 !
b1001 $
#100000000
b1010 !
b1010 $
#110000000
b1011 !
b1011 $
#120000000
b1100 !
b1100 $
#130000000
b1101 !
b1101 $
#140000000
b1110 !
b1110 $
#150000000
b1111 !
b1111 $
#160000000
b0000 !
b0001 "
b0000 $
b0001 %
#170000000
b0001 !
b00000001 #
b0001 $
b00000001 &
#180000000
b0010 !
b00000010 #
b0010 $
b00000010 &
#190000000
b0011 !
b00000011 #
b0011 $
b00000011 &
#200000000
b0100 !
b00000100 #
b0100 $
b00000100 &
#210000000
b0101 !
b00000101 #
b0101 $
b00000101 &
#220000000
b0110 !
b00000110 #
b0110 $
b00000110 &
#230000000
b0111 !
b00000111 #
b0111 $
b00000111 &
#240000000
b1000 !
b00001000 #
b1000 $
b00001000 &
#250000000
b1001 !
b00001001 #
b1001 $
b00001001 &
#260000000
b1010 !
b00001010 #
b1010 $
b00001010 &
#270000000
b1011 !
b00001011 #
b1011 $
b00001011 &
#280000000
b1100 !
b00001100 #
b1100 $
b00001100 &
#290000000
b1101 !
b00001101 #
b1101 $
b00001101 &
#300000000
b1110 !
b00001110 #
b1110 $
b00001110 &
#310000000
b1111 !
b00001111 #
b1111 $
b00001111 &
#320000000
b0000 !
b0010 "
b00000000 #
b0000 $
b0010 %
b00000000 &
#330000000
b0001 !
b00000010 #
b0001 $
b00000010 &
#340000000
b0010 !
b00000100 #
b0010 $
b00000100 &
#350000000
b0011 !
b00000110 #
b0011 $
b00000110 &
#360000000
b0100 !
b00001000 #
b0100 $
b00001000 &
#370000000
b0101 !
b00001010 #
b0101 $
b00001010 &
#380000000
b0110 !
b00001100 #
b0110 $
b00001100 &
#390000000
b0111 !
b00001110 #
b0111 $
b00001110 &
#400000000
b1000 !
b00010000 #
b1000 $
b00010000 &
#410000000
b1001 !
b00010010 #
b1001 $
b00010010 &
#420000000
b1010 !
b00010100 #
b1010 $
b00010100 &
#430000000
b1011 !
b00010110 #
b1011 $
b00010110 &
#440000000
b1100 !
b00011000 #
b1100 $
b00011000 &
#450000000
b1101 !
b00011010 #
b1101 $
b00011010 &
#460000000
b1110 !
b00011100 #
b1110 $
b00011100 &
#470000000
b1111 !
b00011110 #
b1111 $
b00011110 &
#480000000
b0000 !
b0011 "
b00000000 #
b0000 $
b0011 %
b00000000 &
#490000000
b0001 !
b00000011 #
b0001 $
b00000011 &
#500000000
b0010 !
b00000110 #
b0010 $
b00000110 &
#510000000
b0011 !
b00001001 #
b0011 $
b00001001 &
#520000000
b0100 !
b00001100 #
b0100 $
b00001100 &
#530000000
b0101 !
b00001111 #
b0101 $
b00001111 &
#540000000
b0110 !
b00010010 #
b0110 $
b00010010 &
#550000000
b0111 !
b00010101 #
b0111 $
b00010101 &
#560000000
b1000 !
b00011000 #
b1000 $
b00011000 &
#570000000
b1001 !
b00011011 #
b1001 $
b00011011 &
#580000000
b1010 !
b00011110 #
b1010 $
b00011110 &
#590000000
b1011 !
b00100001 #
b1011 $
b00100001 &
#600000000
b1100 !
b00100100 #
b1100 $
b00100100 &
#610000000
b1101 !
b00100111 #
b1101 $
b00100111 &
#620000000
b1110 !
b00101010 #
b1110 $
b00101010 &
#630000000
b1111 !
b00101101 #
b1111 $
b00101101 &
#640000000
b0000 !
b0100 "
b00000000 #
b0000 $
b0100 %
b00000000 &
#650000000
b0001 !
b00000100 #
b0001 $
b00000100 &
#660000000
b0010 !
b00001000 #
b0010 $
b00001000 &
#670000000
b0011 !
b00001100 #
b0011 $
b00001100 &
#680000000
b0100 !
b00010000 #
b0100 $
b00010000 &
#690000000
b0101 !
b00010100 #
b0101 $
b00010100 &
#700000000
b0110 !
b00011000 #
b0110 $
b00011000 &
#710000000
b0111 !
b00011100 #
b0111 $
b00011100 &
#720000000
b1000 !
b00100000 #
b1000 $
b00100000 &
#730000000
b1001 !
b00100100 #
b1001 $
b00100100 &
#740000000
b1010 !
b00101000 #
b1010 $
b00101000 &
#750000000
b1011 !
b00101100 #
b1011 $
b00101100 &
#760000000
b1100 !
b00110000 #
b1100 $
b00110000 &
#770000000
b1101 !
b00110100 #
b1101 $
b00110100 &
#780000000
b1110 !
b00111000 #
b1110 $
b00111000 &
#790000000
b1111 !
b00111100 #
b1111 $
b00111100 &
#800000000
b0000 !
b0101 "
b00000000 #
b0000 $
b0101 %
b00000000 &
#810000000
b0001 !
b00000101 #
b0001 $
b00000101 &
#820000000
b0010 !
b00001010 #
b0010 $
b00001010 &
#830000000
b0011 !
b00001111 #
b0011 $
b00001111 &
#840000000
b0100 !
b00010100 #
b0100 $
b00010100 &
#850000000
b0101 !
b00011001 #
b0101 $
b00011001 &
#860000000
b0110 !
b00011110 #
b0110 $
b00011110 &
#870000000
b0111 !
b00100011 #
b0111 $
b00100011 &
#880000000
b1000 !
b00101000 #
b1000 $
b00101000 &
#890000000
b1001 !
b00101101 #
b1001 $
b00101101 &
#900000000
b1010 !
b00110010 #
b1010 $
b00110010 &
#910000000
b1011 !
b00110111 #
b1011 $
b00110111 &
#920000000
b1100 !
b00111100 #
b1100 $
b00111100 &
#930000000
b1101 !
b01000001 #
b1101 $
b01000001 &
#940000000
b1110 !
b01000110 #
b1110 $
b01000110 &
#950000000
b1111 !
b01001011 #
b1111 $
b01001011 &
#960000000
b0000 !
b0110 "
b00000000 #
b0000 $
b0110 %
b00000000 &
#970000000
b0001 !
b00000110 #
b0001 $
b00000110 &
#980000000
b0010 !
b00001100 #
b0010 $
b00001100 &
#990000000
b0011 !
b00010010 #
b0011 $
b00010010 &
#1000000000
b0100 !
b00011000 #
b0100 $
b00011000 &
#1010000000
b0101 !
b00011110 #
b0101 $
b00011110 &
#1020000000
b0110 !
b00100100 #
b0110 $
b00100100 &
#1030000000
b0111 !
b00101010 #
b0111 $
b00101010 &
#1040000000
b1000 !
b00110000 #
b1000 $
b00110000 &
#1050000000
b1001 !
b00110110 #
b1001 $
b00110110 &
#1060000000
b1010 !
b00111100 #
b1010 $
b00111100 &
#1070000000
b1011 !
b01000010 #
b1011 $
b01000010 &
#1080000000
b1100 !
b01001000 #
b1100 $
b01001000 &
#1090000000
b1101 !
b01001110 #
b1101 $
b01001110 &
#1100000000
b1110 !
b01010100 #
b1110 $
b01010100 &
#1110000000
b1111 !
b01011010 #
b1111 $
b01011010 &
#1120000000
b0000 !
b0111 "
b00000000 #
b0000 $
b0111 %
b00000000 &
#1130000000
b0001 !
b00000111 #
b0001 $
b00000111 &
#1140000000
b0010 !
b00001110 #
b0010 $
b00001110 &
#1150000000
b0011 !
b00010101 #
b0011 $
b00010101 &
#1160000000
b0100 !
b00011100 #
b0100 $
b00011100 &
#1170000000
b0101 !
b00100011 #
b0101 $
b00100011 &
#1180000000
b0110 !
b00101010 #
b0110 $
b00101010 &
#1190000000
b0111 !
b00110001 #
b0111 $
b00110001 &
#1200000000
b1000 !
b00111000 #
b1000 $
b00111000 &
#1210000000
b1001 !
b00111111 #
b1001 $
b00111111 &
#1220000000
b1010 !
b01000110 #
b1010 $
b01000110 &
#1230000000
b1011 !
b01001101 #
b1011 $
b01001101 &
#1240000000
b1100 !
b01010100 #
b1100 $
b01010100 &
#1250000000
b1101 !
b01011011 #
b1101 $
b01011011 &
#1260000000
b1110 !
b01100010 #
b1110 $
b01100010 &
#1270000000
b1111 !
b01101001 #
b1111 $
b01101001 &
#1280000000
b0000 !
b1000 "
b00000000 #
b0000 $
b1000 %
b00000000 &
#1290000000
b0001 !
b00001000 #
b0001 $
b00001000 &
#1300000000
b0010 !
b00010000 #
b0010 $
b00010000 &
#1310000000
b0011 !
b00011000 #
b0011 $
b00011000 &
#1320000000
b0100 !
b00100000 #
b0100 $
b00100000 &
#1330000000
b0101 !
b00101000 #
b0101 $
b00101000 &
#1340000000
b0110 !
b00110000 #
b0110 $
b00110000 &
#1350000000
b0111 !
b00111000 #
b0111 $
b00111000 &
#1360000000
b1000 !
b01000000 #
b1000 $
b01000000 &
#1370000000
b1001 !
b01001000 #
b1001 $
b01001000 &
#1380000000
b1010 !
b01010000 #
b1010 $
b01010000 &
#1390000000
b1011 !
b01011000 #
b1011 $
b01011000 &
#1400000000
b1100 !
b01100000 #
b1100 $
b01100000 &
#1410000000
b1101 !
b01101000 #
b1101 $
b01101000 &
#1420000000
b1110 !
b01110000 #
b1110 $
b01110000 &
#1430000000
b1111 !
b01111000 #
b1111 $
b01111000 &
#1440000000
b0000 !
b1001 "
b00000000 #
b0000 $
b1001 %
b00000000 &
#1450000000
b0001 !
b00001001 #
b0001 $
b00001001 &
#1460000000
b0010 !
b00010010 #
b0010 $
b00010010 &
#1470000000
b0011 !
b00011011 #
b0011 $
b00011011 &
#1480000000
b0100 !
b00100100 #
b0100 $
b00100100 &
#1490000000
b0101 !
b00101101 #
b0101 $
b00101101 &
#1500000000
b0110 !
b00110110 #
b0110 $
b00110110 &
#1510000000
b0111 !
b00111111 #
b0111 $
b00111111 &
#1520000000
b1000 !
b01001000 #
b1000 $
b01001000 &
#1530000000
b1001 !
b01010001 #
b1001 $
b01010001 &
#1540000000
b1010 !
b01011010 #
b1010 $
b01011010 &
#1550000000
b1011 !
b01100011 #
b1011 $
b01100011 &
#1560000000
b1100 !
b01101100 #
b1100 $
b01101100 &
#1570000000
b1101 !
b01110101 #
b1101 $
b01110101 &
#1580000000
b1110 !
b01111110 #
b1110 $
b01111110 &
#1590000000
b1111 !
b10000111 #
b1111 $
b10000111 &
#1600000000
b0000 !
b1010 "
b00000000 #
b0000 $
b1010 %
b00000000 &
#1610000000
b0001 !
b00001010 #
b0001 $
b00001010 &
#1620000000
b0010 !
b00010100 #
b0010 $
b00010100 &
#1630000000
b0011 !
b00011110 #
b0011 $
b00011110 &
#1640000000
b0100 !
b00101000 #
b0100 $
b00101000 &
#1650000000
b0101 !
b00110010 #
b0101 $
b00110010 &
#1660000000
b0110 !
b00111100 #
b0110 $
b00111100 &
#1670000000
b0111 !
b01000110 #
b0111 $
b01000110 &
#1680000000
b1000 !
b01010000 #
b1000 $
b01010000 &
#1690000000
b1001 !
b01011010 #
b1001 $
b01011010 &
#1700000000
b1010 !
b01100100 #
b1010 $
b01100100 &
#1710000000
b1011 !
b01101110 #
b1011 $
b01101110 &
#1720000000
b1100 !
b01111000 #
b1100 $
b01111000 &
#1730000000
b1101 !
b10000010 #
b1101 $
b10000010 &
#1740000000
b1110 !
b10001100 #
b1110 $
b10001100 &
#1750000000
b1111 !
b10010110 #
b1111 $
b10010110 &
#1760000000
b0000 !
b1011 "
b00000000 #
b0000 $
b1011 %
b00000000 &
#1770000000
b0001 !
b00001011 #
b0001 $
b00001011 &
#1780000000
b0010 !
b00010110 #
b0010 $
b00010110 &
#1790000000
b0011 !
b00100001 #
b0011 $
b00100001 &
#1800000000
b0100 !
b00101100 #
b0100 $
b00101100 &
#1810000000
b0101 !
b00110111 #
b0101 $
b00110111 &
#1820000000
b0110 !
b01000010 #
b0110 $
b01000010 &
#1830000000
b0111 !
b01001101 #
b0111 $
b01001101 &
#1840000000
b1000 !
b01011000 #
b1000 $
b01011000 &
#1850000000
b1001 !
b01100011 #
b1001 $
b01100011 &
#1860000000
b1010 !
b01101110 #
b1010 $
b01101110 &
#1870000000
b1011 !
b01111001 #
b1011 $
b01111001 &
#1880000000
b1100 !
b10000100 #
b1100 $
b10000100 &
#1890000000
b1101 !
b10001111 #
b1101 $
b10001111 &
#1900000000
b1110 !
b10011010 #
b1110 $
b10011010 &
#1910000000
b1111 !
b10100101 #
b1111 $
b10100101 &
#1920000000
b0000 !
b1100 "
b00000000 #
b0000 $
b1100 %
b00000000 &
#1930000000
b0001 !
b00001100 #
b0001 $
b00001100 &
#1940000000
b0010 !
b00011000 #
b0010 $
b00011000 &
#1950000000
b0011 !
b00100100 #
b0011 $
b00100100 &
#1960000000
b0100 !
b00110000 #
b0100 $
b00110000 &
#1970000000
b0101 !
b00111100 #
b0101 $
b00111100 &
#1980000000
b0110 !
b01001000 #
b0110 $
b01001000 &
#1990000000
b0111 !
b01010100 #
b0111 $
b01010100 &
#2000000000
b1000 !
b01100000 #
b1000 $
b01100000 &
#2010000000
b1001 !
b01101100 #
b1001 $
b01101100 &
#2020000000
b1010 !
b01111000 #
b1010 $
b01111000 &
#2030000000
b1011 !
b10000100 #
b1011 $
b10000100 &
#2040000000
b1100 !
b10010000 #
b1100 $
b10010000 &
#2050000000
b1101 !
b10011100 #
b1101 $
b10011100 &
#2060000000
b1110 !
b10101000 #
b1110 $
b10101000 &
#2070000000
b1111 !
b10110100 #
b1111 $
b10110100 &
#2080000000
b0000 !
b1101 "
b00000000 #
b0000 $
b1101 %
b00000000 &
#2090000000
b0001 !
b00001101 #
b0001 $
b00001101 &
#2100000000
b0010 !
b00011010 #
b0010 $
b00011010 &
#2110000000
b0011 !
b00100111 #
b0011 $
b00100111 &
#2120000000
b0100 !
b00110100 #
b0100 $
b00110100 &
#2130000000
b0101 !
b01000001 #
b0101 $
b01000001 &
#2140000000
b0110 !
b01001110 #
b0110 $
b01001110 &
#2150000000
b0111 !
b01011011 #
b0111 $
b01011011 &
#2160000000
b1000 !
b01101000 #
b1000 $
b01101000 &
#2170000000
b1001 !
b01110101 #
b1001 $
b01110101 &
#2180000000
b1010 !
b10000010 #
b1010 $
b10000010 &
#2190000000
b1011 !
b10001111 #
b1011 $
b10001111 &
#2200000000
b1100 !
b10011100 #
b1100 $
b10011100 &
#2210000000
b1101 !
b10101001 #
b1101 $
b10101001 &
#2220000000
b1110 !
b10110110 #
b1110 $
b10110110 &
#2230000000
b1111 !
b11000011 #
b1111 $
b11000011 &
#2240000000
b0000 !
b1110 "
b00000000 #
b0000 $
b1110 %
b00000000 &
#2250000000
b0001 !
b00001110 #
b0001 $
b00001110 &
#2260000000
b0010 !
b00011100 #
b0010 $
b00011100 &
#2270000000
b0011 !
b00101010 #
b0011 $
b00101010 &
#2280000000
b0100 !
b00111000 #
b0100 $
b00111000 &
#2290000000
b0101 !
b01000110 #
b0101 $
b01000110 &
#2300000000
b0110 !
b01010100 #
b0110 $
b01010100 &
#2310000000
b0111 !
b01100010 #
b0111 $
b01100010 &
#2320000000
b1000 !
b01110000 #
b1000 $
b01110000 &
#2330000000
b1001 !
b01111110 #
b1001 $
b01111110 &
#2340000000
b1010 !
b10001100 #
b1010 $
b10001100 &
#2350000000
b1011 !
b10011010 #
b1011 $
b10011010 &
#2360000000
b1100 !
b10101000 #
b1100 $
b10101000 &
#2370000000
b1101 !
b10110110 #
b1101 $
b10110110 &
#2380000000
b1110 !
b11000100 #
b1110 $
b11000100 &
#2390000000
b1111 !
b11010010 #
b1111 $
b11010010 &
#2400000000
b0000 !
b1111 "
b00000000 #
b0000 $
b1111 %
b00000000 &
#2410000000
b0001 !
b00001111 #
b0001 $
b00001111 &
#2420000000
b0010 !
b00011110 #
b0010 $
b00011110 &
#2430000000
b0011 !
b00101101 #
b0011 $
b00101101 &
#2440000000
b0100 !
b00111100 #
b0100 $
b00111100 &
#2450000000
b0101 !
b01001011 #
b0101 $
b01001011 &
#2460000000
b0110 !
b01011010 #
b0110 $
b01011010 &
#2470000000
b0111 !
b01101001 #
b0111 $
b01101001 &
#2480000000
b1000 !
b01111000 #
b1000 $
b01111000 &
#2490000000
b1001 !
b10000111 #
b1001 $
b10000111 &
#2500000000
b1010 !
b10010110 #
b1010 $
b10010110 &
#2510000000
b1011 !
b10100101 #
b1011 $
b10100101 &
#2520000000
b1100 !
b10110100 #
b1100 $
b10110100 &
#2530000000
b1101 !
b11000011 #
b1101 $
b11000011 &
#2540000000
b1110 !
b11010010 #
b1110 $
b11010010 &
#2550000000
b1111 !
b11100001 #
b1111 $
b11100001 &
#2560000000
b0000 !
b0000 "
b00000000 #
b0000 $
b0000 %
b00000000 &
