2/full_adder2/or3_gate.vhd
--------------------------------------------
-- Module Name: full_adder_structural
--------------------------------------------

library IEEE;
use IEEE.STD_LOGIC_1164.ALL;

Entity or3 Is
port (
		i0 : in STD_LOGIC;
        i1 : in STD_LOGIC;  
        i2 : in STD_LOGIC;        
        o : out STD_LOGIC
	);
end or3;

architecture dataflow of or3 is
begin
	o <= i0 OR i1 OR i2;		
end dataflow;

2/ejemplos_sumador/half_adder/estructural/and2.vhd
--------------------------------------------
-- Module Name: fulladder_dataflow
--------------------------------------------

library IEEE;
use IEEE.STD_LOGIC_1164.ALL;


Entity and2 Is
port(
		i0  	 : in STD_LOGIC;
		i1  	 : in STD_LOGIC;
		o        : out STD_LOGIC
	);
end and2;

Architecture and2_arch of and2 Is

begin
    o <= i0 AND i1;
end and2_arch;

2/full_adder2/xor3_gate.vhd
--------------------------------------------
-- Module Name: full_adder_structural
--------------------------------------------

library IEEE;
use IEEE.STD_LOGIC_1164.ALL;


Entity xor3 Is
port (
		i0 : in STD_LOGIC;
        i1 : in STD_LOGIC;        
        i2 : in STD_LOGIC;        
        o : out STD_LOGIC
	);
end xor3;

architecture dataflow of xor3 is
begin
	o <= i0 XOR i1 XOR i2;		
end dataflow;

2/full_adder2/full_adder.vhd
library IEEE;
use IEEE.STD_LOGIC_1164.ALL;

Entity full_adder Is
port (
        x : in STD_LOGIC;
        y : in STD_LOGIC;
        cin : in STD_LOGIC;
        -- salidas forma dataflow
        s_df : out STD_LOGIC;
        cout_df: out STD_LOGIC;
        -- salidas forma structural
        s_struct : out STD_LOGIC;
        cout_struct: out STD_LOGIC;
        -- salidas forma behavioral
        s_behav : out STD_LOGIC;
        cout_behav: out STD_LOGIC
    );
end full_adder;

Architecture behavior of full_adder Is

-- Señales para la parte dataflow
Signal x_y : STD_LOGIC;
Signal x_cin : STD_LOGIC;
Signal y_cin : STD_LOGIC;

-- Componets y signals para la parte de la descripcion estructural

component and2 port
( i0, i1: in STD_LOGIC;
  o : out STD_LOGIC);
end component;

component or3 port
( i0, i1, i2: in STD_LOGIC;
  o : out STD_LOGIC);
end component;

component xor3 port
( i0, i1, i2: in STD_LOGIC;
  o : out STD_LOGIC);
end component;

Signal x_y_s : STD_LOGIC;
Signal x_cin_s : STD_LOGIC;
Signal y_cin_S : STD_LOGIC;

begin   
    -- ******************************************
    -- Parte dataflow
    -- ******************************************
    -- Forma 1
    
    s_df <= x xor y xor cin;
    x_y <= x and y;
    x_cin <= x and cin;
    y_cin <= y and cin;
    cout_df <= x_y or x_cin or y_cin;

    -- Forma 2:  Casos usando la asignacion condicional
 
    --- ---------------------------
        --- TABLA DE VERDAD FULL_ADDER
        --- ---------------------------
        --- | x | y | cin || s | cout |
        --- ---------------------------
        --- | 0 | 0 |  0  || 0 |  0   |
        --- | 0 | 0 |  1  || 1 |  0   |
        --- | 0 | 1 |  0  || 1 |  0   |
        --- | 0 | 1 |  1  || 0 |  1   |
        --- | 1 | 0 |  0  || 1 |  0   |
        --- | 1 | 0 |  1  || 0 |  1   |
        --- | 1 | 1 |  0  || 0 |  1   |
        --- | 1 | 1 |  1  || 1 |  1   |
        --- ---------------------------
    ---

    -- s_df <= '1' when x_y_cin = "001" else
    --       '1' when x_y_cin = "010" else
    --       '1' when x_y_cin = "100" else
    --       '1' when x_y_cin = "111" else
    --       '0';
    
    -- cout_df <= '1' when (x = '0' and y = '1' and cin = '1') else
    --          '1' when (x = '1' and y = '0' and cin = '1') else
    --          '1' when (x = '1' and y = '1' and cin = '0') else
    --          '1' when (x = '1' and y = '1' and cin = '1') else
    --          '0';


    -- ******************************************
    -- Parte structural
    -- ******************************************

    x1 : xor3 port map (i0 => x, i1 => y, i2 => cin, o => s_struct);
	a1 : and2 port map (i0 => x, i1 => y, o => x_y_s);
    a2 : and2 port map (i0 => x, i1 => cin, o => x_cin_s);
    a3 : and2 port map (i0 => y, i1 => cin, o => y_cin_s);
	o1 : or3 port map (i0 => x_y, i1 => x_cin, i2 => y_cin, o => cout_struct);  

    -- ******************************************
    -- Parte behavioral 
    -- ******************************************
    -- Se hacce uso de process...
    process (x,y,cin)

    Variable x_y_v : STD_LOGIC;
    Variable x_cin_v : STD_LOGIC;
    Variable y_cin_v : STD_LOGIC;

    begin
    s_behav <= x xor y xor cin;
    x_y_v := x and y;
    x_cin_v := x and cin;
    y_cin_v := y and cin;
    cout_behav <= x_y_v or x_cin_v or y_cin_v;
    
    end process;
    
end behavior;

2/full_adder2/full_adder_tb.vhd
library IEEE;
use IEEE.STD_LOGIC_1164.ALL;
use IEEE.STD_LOGIC_ARITH.ALL;
use IEEE.STD_LOGIC_UNSIGNED.ALL;

Entity full_adder_tb Is
end full_adder_tb;

Architecture behavior of full_adder_tb Is
	
    Component full_adder Is
    port (
        x : in STD_LOGIC;
        y : in STD_LOGIC;
        cin : in STD_LOGIC;
        -- salidas forma dataflow
        s_df : out STD_LOGIC;
        cout_df: out STD_LOGIC;
        -- salidas forma structural
        s_struct : out STD_LOGIC;
        cout_struct: out STD_LOGIC;
        -- salidas forma behavioral
        s_behav : out STD_LOGIC;
        cout_behav: out STD_LOGIC
    );
    end Component;
	
	Signal x_y_cin_sig 	    : STD_LOGIC_VECTOR(2 DOWNTO 0) := "000";
    Signal out_dataflow    	: STD_LOGIC_VECTOR(1 DOWNTO 0);
    Signal out_struct   	: STD_LOGIC_VECTOR(1 DOWNTO 0);
	Signal out_behav    	: STD_LOGIC_VECTOR(1 DOWNTO 0);

	
begin 
	DUT:  full_adder PORT MAP (
        -- Entratas
		x => x_y_cin_sig(2),
		y => x_y_cin_sig(1),
        cin => x_y_cin_sig(0),
        -- Salidas formadataflow
        s_df => out_dataflow(1),
        cout_df => out_dataflow(0),
        -- salidas forma dataflow
		s_struct => out_struct(1),
        cout_struct => out_struct(0),
        -- salidas forma behav
        s_behav => out_behav(1),
        cout_behav => out_behav(0)
    );


    -- Generacion de la señal de test
    process

	begin
		wait for 20 ns;
		for k in 0 to 7 loop   	  
		  x_y_cin_sig <= x_y_cin_sig + '1';
		  wait for 20 ns;		  		  
		end loop;  
		wait;							 
	
    end process;
end behavior;

2/full_adder2/full_adder_tb.vcd
$date
  Mon Jul 29 18:21:18 2019
$end
$version
  GHDL v0
$end
$timescale
  1 fs
$end
$scope module standard $end
$upscope $end
$scope module std_logic_1164 $end
$upscope $end
$scope module std_logic_arith $end
$upscope $end
$scope module std_logic_unsigned $end
$upscope $end
$scope module full_adder_tb $end
$var reg 3 ! x_y_cin_sig[2:0] $end
$var reg 2 " out_dataflow[1:0] $end
$var reg 2 # out_struct[1:0] $end
$var reg 2 $ out_behav[1:0] $end
$scope module dut $end
$var reg 1 % x $end
$var reg 1 & y $end
$var reg 1 ' cin $end
$var reg 1 ( s_df $end
$var reg 1 ) cout_df $end
$var reg 1 * s_struct $end
$var reg 1 + cout_struct $end
$var reg 1 , s_behav $end
$var reg 1 - cout_behav $end
$var reg 1 . x_y $end
$var reg 1 / x_cin $end
$var reg 1 0 y_cin $end
$var reg 1 1 x_y_s $end
$var reg 1 2 x_cin_s $end
$var reg 1 3 y_cin_s $end
$scope module x1 $end
$var reg 1 4 i0 $end
$var reg 1 5 i1 $end
$var reg 1 6 i2 $end
$var reg 1 7 o $end
$upscope $end
$scope module a1 $end
$var reg 1 8 i0 $end
$var reg 1 9 i1 $end
$var reg 1 : o $end
$upscope $end
$scope module a2 $end
$var reg 1 ; i0 $end
$var reg 1 < i1 $end
$var reg 1 = o $end
$upscope $end
$scope module a3 $end
$var reg 1 > i0 $end
$var reg 1 ? i1 $end
$var reg 1 @ o $end
$upscope $end
$scope module o1 $end
$var reg 1 A i0 $end
$var reg 1 B i1 $end
$var reg 1 C i2 $end
$var reg 1 D o $end
$upscope $end
$upscope $end
$upscope $end
$enddefinitions $end
#0
b000 !
b00 "
b00 #
b00 $
0%
0&
0'
0(
0)
0*
0+
0,
0-
0.
0/
00
01
02
03
04
05
06
07
08
09
0:
0;
0<
0=
0>
0?
0@
0A
0B
0C
0D
#20000000
b001 !
b10 "
b10 #
b10 $
1'
1(
1*
1,
16
17
1<
1?
#40000000
b010 !
1&
0'
15
06
19
0<
1>
0?
#60000000
b011 !
b01 "
b01 #
b01 $
1'
0(
1)
0*
1+
0,
1-
10
13
16
07
1<
1?
1@
1C
1D
#80000000
b100 !
b10 "
b10 #
b10 $
1%
0&
0'
1(
0)
1*
0+
1,
0-
00
03
14
05
06
17
18
09
1;
0<
0>
0?
0@
0C
0D
#100000000
b101 !
b01 "
b01 #
b01 $
1'
0(
1)
0*
1+
0,
1-
1/
12
16
07
1<
1=
1?
1B
1D
#120000000
b110 !
1&
0'
1.
0/
11
02
15
06
19
1:
0<
0=
1>
0?
1A
0B
#140000000
b111 !
b11 "
b11 #
b11 $
1'
1(
1*
1,
1/
10
12
13
16
17
1<
1=
1?
1@
1B
1C
#160000000
b000 !
b00 "
b00 #
b00 $
0%
0&
0'
0(
0)
0*
0+
0,
0-
0.
0/
00
01
02
03
04
05
06
07
08
09
0:
0;
0<
0=
0>
0?
0@
0A
0B
0C
0D
