4/conceptos_previos/ejemplo1/simple_int_counter.vhd
-- Counters in VHDL Using the Type UNSIGNED --
library ieee;
use ieee.std_logic_1164.all;
use ieee.numeric_std.all;

ENTITY simple_int_counter IS
	PORT(
		clock : IN STD_LOGIC;
		reset : IN STD_LOGIC;
		q 	  : OUT INTEGER RANGE 0 TO 255
	);
END simple_int_counter;


ARCHITECTURE counter OF simple_int_counter IS

BEGIN
	PROCESS (clock, reset)
		VARIABLE count : INTEGER RANGE 0 to 255;
	BEGIN
		IF (reset = '0') THEN
			count := 0;
		ELSE
			IF (clock'EVENT AND clock = '1') THEN				
				IF (count = 255) THEN
					count := 0;
				ELSE
					count := count + 1;
				END IF;
			END IF;
		END IF;
		q <= count;
	END PROCESS;
END counter;

4/conceptos_previos/contadores/ejemplo2/simple_int_counter_tb.vhd
library ieee;
use ieee.std_logic_1164.all;
use ieee.numeric_std.all;

entity simple_int_counter_tb is
end simple_int_counter_tb;

architecture test_arch of simple_int_counter_tb is
    
    -- Declaracion de componentes

    component simple_int_counter is
	      port(
		          clock : IN STD_LOGIC;
		          reset : IN STD_LOGIC;
		          q : OUT INTEGER RANGE 0 TO 255
	      );
    end component;
    
    -- Señales empleadas

    signal clock, reset: std_logic;   
    signal q: integer range 0 to 255;   

begin

  DUT: simple_int_counter
	Port map (
        clock => clock,
        reset => reset,
        q => q
  );
  
  clock_gen_signal: process
  begin
    clock <= '0';
    wait for 10 ns;
    clock <= '1';
    wait for 10 ns;
  end process;

  clear_gen_signal: process
  begin
    reset <= '1';
    wait for 200 ns;     -- 200 ns
    reset <= '0';
    wait for 200 ns;     -- 200 ns
    reset <= '1';
    wait;
  end process;

end test_arch;

4/conceptos_previos/contadores/ejemplo2/simple_int_counter_results.vcd
$date
  Sun Apr 26 19:57:13 2020
$end
$version
  GHDL v0
$end
$timescale
  1 fs
$end
$scope module standard $end
$upscope $end
$scope module std_logic_1164 $end
$upscope $end
$scope module numeric_std $end
$upscope $end
$scope module simple_int_counter_tb $end
$var reg 1 ! clock $end
$var reg 1 " reset $end
$var integer 32 # q $end
$scope module dut $end
$var reg 1 $ clock $end
$var reg 1 % reset $end
$var integer 32 & q $end
$upscope $end
$upscope $end
$enddefinitions $end
#0
0!
1"
b0 #
0$
1%
b0 &
#10000000
1!
b1 #
1$
b1 &
#20000000
0!
0$
#30000000
1!
b10 #
1$
b10 &
#40000000
0!
0$
#50000000
1!
b11 #
1$
b11 &
#60000000
0!
0$
#70000000
1!
b100 #
1$
b100 &
#80000000
0!
0$
#90000000
1!
b101 #
1$
b101 &
#100000000
0!
0$
#110000000
1!
b110 #
1$
b110 &
#120000000
0!
0$
#130000000
1!
b111 #
1$
b111 &
#140000000
0!
0$
#150000000
1!
b1000 #
1$
b1000 &
#160000000
0!
0$
#170000000
1!
b1001 #
1$
b1001 &
#180000000
0!
0$
#190000000
1!
b1010 #
1$
b1010 &
#200000000
0!
0"
0$
0%
#210000000
1!
b0 #
1$
b0 &
#220000000
0!
0$
#230000000
1!
1$
#240000000
0!
0$
#250000000
1!
1$
#260000000
0!
0$
#270000000
1!
1$
#280000000
0!
0$
#290000000
1!
1$
#300000000
0!
0$
#310000000
1!
1$
#320000000
0!
0$
#330000000
1!
1$
#340000000
0!
0$
#350000000
1!
1$
#360000000
0!
0$
#370000000
1!
1$
#380000000
0!
0$
#390000000
1!
1$
#400000000
0!
1"
0$
1%
#410000000
1!
b1 #
1$
b1 &
#420000000
0!
0$
#430000000
1!
b10 #
1$
b10 &
#440000000
0!
0$
#450000000
1!
b11 #
1$
b11 &
#460000000
0!
0$
#470000000
1!
b100 #
1$
b100 &
#480000000
0!
0$
#490000000
1!
b101 #
1$
b101 &
#500000000
0!
0$
#510000000
1!
b110 #
1$
b110 &
#520000000
0!
0$
#530000000
1!
b111 #
1$
b111 &
#540000000
0!
0$
#550000000
1!
b1000 #
1$
b1000 &
#560000000
0!
0$
#570000000
1!
b1001 #
1$
b1001 &
#580000000
0!
0$
#590000000
1!
b1010 #
1$
b1010 &
#600000000
0!
0$
#610000000
1!
b1011 #
1$
b1011 &
#620000000
0!
0$
#630000000
1!
b1100 #
1$
b1100 &
#640000000
0!
0$
#650000000
1!
b1101 #
1$
b1101 &
#660000000
0!
0$
#670000000
1!
b1110 #
1$
b1110 &
#680000000
0!
0$
#690000000
1!
b1111 #
1$
b1111 &
#700000000
0!
0$
#710000000
1!
b10000 #
1$
b10000 &
#720000000
0!
0$
#730000000
1!
b10001 #
1$
b10001 &
#740000000
0!
0$
#750000000
1!
b10010 #
1$
b10010 &
#760000000
0!
0$
#770000000
1!
b10011 #
1$
b10011 &
#780000000
0!
0$
#790000000
1!
b10100 #
1$
b10100 &
#800000000
0!
0$
#810000000
1!
b10101 #
1$
b10101 &
#820000000
0!
0$
#830000000
1!
b10110 #
1$
b10110 &
#840000000
0!
0$
#850000000
1!
b10111 #
1$
b10111 &
#860000000
0!
0$
#870000000
1!
b11000 #
1$
b11000 &
#880000000
0!
0$
#890000000
1!
b11001 #
1$
b11001 &
#900000000
0!
0$
#910000000
1!
b11010 #
1$
b11010 &
#920000000
0!
0$
#930000000
1!
b11011 #
1$
b11011 &
#940000000
0!
0$
#950000000
1!
b11100 #
1$
b11100 &
#960000000
0!
0$
#970000000
1!
b11101 #
1$
b11101 &
#980000000
0!
0$
#990000000
1!
b11110 #
1$
b11110 &
#1000000000
0!
0$
#1010000000
1!
b11111 #
1$
b11111 &
#1020000000
0!
0$
#1030000000
1!
b100000 #
1$
b100000 &
#1040000000
0!
0$
#1050000000
1!
b100001 #
1$
b100001 &
#1060000000
0!
0$
#1070000000
1!
b100010 #
1$
b100010 &
#1080000000
0!
0$
#1090000000
1!
b100011 #
1$
b100011 &
#1100000000
0!
0$
#1110000000
1!
b100100 #
1$
b100100 &
#1120000000
0!
0$
#1130000000
1!
b100101 #
1$
b100101 &
#1140000000
0!
0$
#1150000000
1!
b100110 #
1$
b100110 &
#1160000000
0!
0$
#1170000000
1!
b100111 #
1$
b100111 &
#1180000000
0!
0$
#1190000000
1!
b101000 #
1$
b101000 &
#1200000000
0!
0$
#1210000000
1!
b101001 #
1$
b101001 &
#1220000000
0!
0$
#1230000000
1!
b101010 #
1$
b101010 &
#1240000000
0!
0$
#1250000000
1!
b101011 #
1$
b101011 &
#1260000000
0!
0$
#1270000000
1!
b101100 #
1$
b101100 &
#1280000000
0!
0$
#1290000000
1!
b101101 #
1$
b101101 &
#1300000000
0!
0$
#1310000000
1!
b101110 #
1$
b101110 &
#1320000000
0!
0$
#1330000000
1!
b101111 #
1$
b101111 &
#1340000000
0!
0$
#1350000000
1!
b110000 #
1$
b110000 &
#1360000000
0!
0$
#1370000000
1!
b110001 #
1$
b110001 &
#1380000000
0!
0$
#1390000000
1!
b110010 #
1$
b110010 &
#1400000000
0!
0$
#1410000000
1!
b110011 #
1$
b110011 &
#1420000000
0!
0$
#1430000000
1!
b110100 #
1$
b110100 &
#1440000000
0!
0$
#1450000000
1!
b110101 #
1$
b110101 &
#1460000000
0!
0$
#1470000000
1!
b110110 #
1$
b110110 &
#1480000000
0!
0$
#1490000000
1!
b110111 #
1$
b110111 &
#1500000000
0!
0$
#1510000000
1!
b111000 #
1$
b111000 &
#1520000000
0!
0$
#1530000000
1!
b111001 #
1$
b111001 &
#1540000000
0!
0$
#1550000000
1!
b111010 #
1$
b111010 &
#1560000000
0!
0$
#1570000000
1!
b111011 #
1$
b111011 &
#1580000000
0!
0$
#1590000000
1!
b111100 #
1$
b111100 &
#1600000000
0!
0$
#1610000000
1!
b111101 #
1$
b111101 &
#1620000000
0!
0$
#1630000000
1!
b111110 #
1$
b111110 &
#1640000000
0!
0$
#1650000000
1!
b111111 #
1$
b111111 &
#1660000000
0!
0$
#1670000000
1!
b1000000 #
1$
b1000000 &
#1680000000
0!
0$
#1690000000
1!
b1000001 #
1$
b1000001 &
#1700000000
0!
0$
#1710000000
1!
b1000010 #
1$
b1000010 &
#1720000000
0!
0$
#1730000000
1!
b1000011 #
1$
b1000011 &
#1740000000
0!
0$
#1750000000
1!
b1000100 #
1$
b1000100 &
#1760000000
0!
0$
#1770000000
1!
b1000101 #
1$
b1000101 &
#1780000000
0!
0$
#1790000000
1!
b1000110 #
1$
b1000110 &
#1800000000
0!
0$
#1810000000
1!
b1000111 #
1$
b1000111 &
#1820000000
0!
0$
#1830000000
1!
b1001000 #
1$
b1001000 &
#1840000000
0!
0$
#1850000000
1!
b1001001 #
1$
b1001001 &
#1860000000
0!
0$
#1870000000
1!
b1001010 #
1$
b1001010 &
#1880000000
0!
0$
#1890000000
1!
b1001011 #
1$
b1001011 &
#1900000000
0!
0$
#1910000000
1!
b1001100 #
1$
b1001100 &
#1920000000
0!
0$
#1930000000
1!
b1001101 #
1$
b1001101 &
#1940000000
0!
0$
#1950000000
1!
b1001110 #
1$
b1001110 &
#1960000000
0!
0$
#1970000000
1!
b1001111 #
1$
b1001111 &
#1980000000
0!
0$
#1990000000
1!
b1010000 #
1$
b1010000 &
#2000000000
0!
0$
#2010000000
1!
b1010001 #
1$
b1010001 &
#2020000000
0!
0$
#2030000000
1!
b1010010 #
1$
b1010010 &
#2040000000
0!
0$
#2050000000
1!
b1010011 #
1$
b1010011 &
#2060000000
0!
0$
#2070000000
1!
b1010100 #
1$
b1010100 &
#2080000000
0!
0$
#2090000000
1!
b1010101 #
1$
b1010101 &
#2100000000
0!
0$
#2110000000
1!
b1010110 #
1$
b1010110 &
#2120000000
0!
0$
#2130000000
1!
b1010111 #
1$
b1010111 &
#2140000000
0!
0$
#2150000000
1!
b1011000 #
1$
b1011000 &
#2160000000
0!
0$
#2170000000
1!
b1011001 #
1$
b1011001 &
#2180000000
0!
0$
#2190000000
1!
b1011010 #
1$
b1011010 &
#2200000000
0!
0$
#2210000000
1!
b1011011 #
1$
b1011011 &
#2220000000
0!
0$
#2230000000
1!
b1011100 #
1$
b1011100 &
#2240000000
0!
0$
#2250000000
1!
b1011101 #
1$
b1011101 &
#2260000000
0!
0$
#2270000000
1!
b1011110 #
1$
b1011110 &
#2280000000
0!
0$
#2290000000
1!
b1011111 #
1$
b1011111 &
#2300000000
0!
0$
#2310000000
1!
b1100000 #
1$
b1100000 &
#2320000000
0!
0$
#2330000000
1!
b1100001 #
1$
b1100001 &
#2340000000
0!
0$
#2350000000
1!
b1100010 #
1$
b1100010 &
#2360000000
0!
0$
#2370000000
1!
b1100011 #
1$
b1100011 &
#2380000000
0!
0$
#2390000000
1!
b1100100 #
1$
b1100100 &
#2400000000
0!
0$
#2410000000
1!
b1100101 #
1$
b1100101 &
#2420000000
0!
0$
#2430000000
1!
b1100110 #
1$
b1100110 &
#2440000000
0!
0$
#2450000000
1!
b1100111 #
1$
b1100111 &
#2460000000
0!
0$
#2470000000
1!
b1101000 #
1$
b1101000 &
#2480000000
0!
0$
#2490000000
1!
b1101001 #
1$
b1101001 &
#2500000000
0!
0$
#2510000000
1!
b1101010 #
1$
b1101010 &
#2520000000
0!
0$
#2530000000
1!
b1101011 #
1$
b1101011 &
#2540000000
0!
0$
#2550000000
1!
b1101100 #
1$
b1101100 &
#2560000000
0!
0$
#2570000000
1!
b1101101 #
1$
b1101101 &
#2580000000
0!
0$
#2590000000
1!
b1101110 #
1$
b1101110 &
#2600000000
0!
0$
#2610000000
1!
b1101111 #
1$
b1101111 &
#2620000000
0!
0$
#2630000000
1!
b1110000 #
1$
b1110000 &
#2640000000
0!
0$
#2650000000
1!
b1110001 #
1$
b1110001 &
#2660000000
0!
0$
#2670000000
1!
b1110010 #
1$
b1110010 &
#2680000000
0!
0$
#2690000000
1!
b1110011 #
1$
b1110011 &
#2700000000
0!
0$
#2710000000
1!
b1110100 #
1$
b1110100 &
#2720000000
0!
0$
#2730000000
1!
b1110101 #
1$
b1110101 &
#2740000000
0!
0$
#2750000000
1!
b1110110 #
1$
b1110110 &
#2760000000
0!
0$
#2770000000
1!
b1110111 #
1$
b1110111 &
#2780000000
0!
0$
#2790000000
1!
b1111000 #
1$
b1111000 &
#2800000000
0!
0$
#2810000000
1!
b1111001 #
1$
b1111001 &
#2820000000
0!
0$
#2830000000
1!
b1111010 #
1$
b1111010 &
#2840000000
0!
0$
#2850000000
1!
b1111011 #
1$
b1111011 &
#2860000000
0!
0$
#2870000000
1!
b1111100 #
1$
b1111100 &
#2880000000
0!
0$
#2890000000
1!
b1111101 #
1$
b1111101 &
#2900000000
0!
0$
#2910000000
1!
b1111110 #
1$
b1111110 &
#2920000000
0!
0$
#2930000000
1!
b1111111 #
1$
b1111111 &
#2940000000
0!
0$
#2950000000
1!
b10000000 #
1$
b10000000 &
#2960000000
0!
0$
#2970000000
1!
b10000001 #
1$
b10000001 &
#2980000000
0!
0$
#2990000000
1!
b10000010 #
1$
b10000010 &
#3000000000
0!
0$
#3010000000
1!
b10000011 #
1$
b10000011 &
#3020000000
0!
0$
#3030000000
1!
b10000100 #
1$
b10000100 &
#3040000000
0!
0$
#3050000000
1!
b10000101 #
1$
b10000101 &
#3060000000
0!
0$
#3070000000
1!
b10000110 #
1$
b10000110 &
#3080000000
0!
0$
#3090000000
1!
b10000111 #
1$
b10000111 &
#3100000000
0!
0$
#3110000000
1!
b10001000 #
1$
b10001000 &
#3120000000
0!
0$
#3130000000
1!
b10001001 #
1$
b10001001 &
#3140000000
0!
0$
#3150000000
1!
b10001010 #
1$
b10001010 &
#3160000000
0!
0$
#3170000000
1!
b10001011 #
1$
b10001011 &
#3180000000
0!
0$
#3190000000
1!
b10001100 #
1$
b10001100 &
#3200000000
0!
0$
#3210000000
1!
b10001101 #
1$
b10001101 &
#3220000000
0!
0$
#3230000000
1!
b10001110 #
1$
b10001110 &
#3240000000
0!
0$
#3250000000
1!
b10001111 #
1$
b10001111 &
#3260000000
0!
0$
#3270000000
1!
b10010000 #
1$
b10010000 &
#3280000000
0!
0$
#3290000000
1!
b10010001 #
1$
b10010001 &
#3300000000
0!
0$
#3310000000
1!
b10010010 #
1$
b10010010 &
#3320000000
0!
0$
#3330000000
1!
b10010011 #
1$
b10010011 &
#3340000000
0!
0$
#3350000000
1!
b10010100 #
1$
b10010100 &
#3360000000
0!
0$
#3370000000
1!
b10010101 #
1$
b10010101 &
#3380000000
0!
0$
#3390000000
1!
b10010110 #
1$
b10010110 &
#3400000000
0!
0$
#3410000000
1!
b10010111 #
1$
b10010111 &
#3420000000
0!
0$
#3430000000
1!
b10011000 #
1$
b10011000 &
#3440000000
0!
0$
#3450000000
1!
b10011001 #
1$
b10011001 &
#3460000000
0!
0$
#3470000000
1!
b10011010 #
1$
b10011010 &
#3480000000
0!
0$
#3490000000
1!
b10011011 #
1$
b10011011 &
#3500000000
0!
0$
#3510000000
1!
b10011100 #
1$
b10011100 &
#3520000000
0!
0$
#3530000000
1!
b10011101 #
1$
b10011101 &
#3540000000
0!
0$
#3550000000
1!
b10011110 #
1$
b10011110 &
#3560000000
0!
0$
#3570000000
1!
b10011111 #
1$
b10011111 &
#3580000000
0!
0$
#3590000000
1!
b10100000 #
1$
b10100000 &
#3600000000
0!
0$
#3610000000
1!
b10100001 #
1$
b10100001 &
#3620000000
0!
0$
#3630000000
1!
b10100010 #
1$
b10100010 &
#3640000000
0!
0$
#3650000000
1!
b10100011 #
1$
b10100011 &
#3660000000
0!
0$
#3670000000
1!
b10100100 #
1$
b10100100 &
#3680000000
0!
0$
#3690000000
1!
b10100101 #
1$
b10100101 &
#3700000000
0!
0$
#3710000000
1!
b10100110 #
1$
b10100110 &
#3720000000
0!
0$
#3730000000
1!
b10100111 #
1$
b10100111 &
#3740000000
0!
0$
#3750000000
1!
b10101000 #
1$
b10101000 &
#3760000000
0!
0$
#3770000000
1!
b10101001 #
1$
b10101001 &
#3780000000
0!
0$
#3790000000
1!
b10101010 #
1$
b10101010 &
#3800000000
0!
0$
#3810000000
1!
b10101011 #
1$
b10101011 &
#3820000000
0!
0$
#3830000000
1!
b10101100 #
1$
b10101100 &
#3840000000
0!
0$
#3850000000
1!
b10101101 #
1$
b10101101 &
#3860000000
0!
0$
#3870000000
1!
b10101110 #
1$
b10101110 &
#3880000000
0!
0$
#3890000000
1!
b10101111 #
1$
b10101111 &
#3900000000
0!
0$
#3910000000
1!
b10110000 #
1$
b10110000 &
#3920000000
0!
0$
#3930000000
1!
b10110001 #
1$
b10110001 &
#3940000000
0!
0$
#3950000000
1!
b10110010 #
1$
b10110010 &
#3960000000
0!
0$
#3970000000
1!
b10110011 #
1$
b10110011 &
#3980000000
0!
0$
#3990000000
1!
b10110100 #
1$
b10110100 &
#4000000000
0!
0$
#4010000000
1!
b10110101 #
1$
b10110101 &
#4020000000
0!
0$
#4030000000
1!
b10110110 #
1$
b10110110 &
#4040000000
0!
0$
#4050000000
1!
b10110111 #
1$
b10110111 &
#4060000000
0!
0$
#4070000000
1!
b10111000 #
1$
b10111000 &
#4080000000
0!
0$
#4090000000
1!
b10111001 #
1$
b10111001 &
#4100000000
0!
0$
#4110000000
1!
b10111010 #
1$
b10111010 &
#4120000000
0!
0$
#4130000000
1!
b10111011 #
1$
b10111011 &
#4140000000
0!
0$
#4150000000
1!
b10111100 #
1$
b10111100 &
#4160000000
0!
0$
#4170000000
1!
b10111101 #
1$
b10111101 &
#4180000000
0!
0$
#4190000000
1!
b10111110 #
1$
b10111110 &
#4200000000
0!
0$
#4210000000
1!
b10111111 #
1$
b10111111 &
#4220000000
0!
0$
#4230000000
1!
b11000000 #
1$
b11000000 &
#4240000000
0!
0$
#4250000000
1!
b11000001 #
1$
b11000001 &
#4260000000
0!
0$
#4270000000
1!
b11000010 #
1$
b11000010 &
#4280000000
0!
0$
#4290000000
1!
b11000011 #
1$
b11000011 &
#4300000000
0!
0$
#4310000000
1!
b11000100 #
1$
b11000100 &
#4320000000
0!
0$
#4330000000
1!
b11000101 #
1$
b11000101 &
#4340000000
0!
0$
#4350000000
1!
b11000110 #
1$
b11000110 &
#4360000000
0!
0$
#4370000000
1!
b11000111 #
1$
b11000111 &
#4380000000
0!
0$
#4390000000
1!
b11001000 #
1$
b11001000 &
#4400000000
0!
0$
#4410000000
1!
b11001001 #
1$
b11001001 &
#4420000000
0!
0$
#4430000000
1!
b11001010 #
1$
b11001010 &
#4440000000
0!
0$
#4450000000
1!
b11001011 #
1$
b11001011 &
#4460000000
0!
0$
#4470000000
1!
b11001100 #
1$
b11001100 &
#4480000000
0!
0$
#4490000000
1!
b11001101 #
1$
b11001101 &
#4500000000
0!
0$
#4510000000
1!
b11001110 #
1$
b11001110 &
#4520000000
0!
0$
#4530000000
1!
b11001111 #
1$
b11001111 &
#4540000000
0!
0$
#4550000000
1!
b11010000 #
1$
b11010000 &
#4560000000
0!
0$
#4570000000
1!
b11010001 #
1$
b11010001 &
#4580000000
0!
0$
#4590000000
1!
b11010010 #
1$
b11010010 &
#4600000000
0!
0$
#4610000000
1!
b11010011 #
1$
b11010011 &
#4620000000
0!
0$
#4630000000
1!
b11010100 #
1$
b11010100 &
#4640000000
0!
0$
#4650000000
1!
b11010101 #
1$
b11010101 &
#4660000000
0!
0$
#4670000000
1!
b11010110 #
1$
b11010110 &
#4680000000
0!
0$
#4690000000
1!
b11010111 #
1$
b11010111 &
#4700000000
0!
0$
#4710000000
1!
b11011000 #
1$
b11011000 &
#4720000000
0!
0$
#4730000000
1!
b11011001 #
1$
b11011001 &
#4740000000
0!
0$
#4750000000
1!
b11011010 #
1$
b11011010 &
#4760000000
0!
0$
#4770000000
1!
b11011011 #
1$
b11011011 &
#4780000000
0!
0$
#4790000000
1!
b11011100 #
1$
b11011100 &
#4800000000
0!
0$
#4810000000
1!
b11011101 #
1$
b11011101 &
#4820000000
0!
0$
#4830000000
1!
b11011110 #
1$
b11011110 &
#4840000000
0!
0$
#4850000000
1!
b11011111 #
1$
b11011111 &
#4860000000
0!
0$
#4870000000
1!
b11100000 #
1$
b11100000 &
#4880000000
0!
0$
#4890000000
1!
b11100001 #
1$
b11100001 &
#4900000000
0!
0$
#4910000000
1!
b11100010 #
1$
b11100010 &
#4920000000
0!
0$
#4930000000
1!
b11100011 #
1$
b11100011 &
#4940000000
0!
0$
#4950000000
1!
b11100100 #
1$
b11100100 &
#4960000000
0!
0$
#4970000000
1!
b11100101 #
1$
b11100101 &
#4980000000
0!
0$
#4990000000
1!
b11100110 #
1$
b11100110 &
#5000000000
0!
0$
#5010000000
1!
b11100111 #
1$
b11100111 &
#5020000000
0!
0$
#5030000000
1!
b11101000 #
1$
b11101000 &
#5040000000
0!
0$
#5050000000
1!
b11101001 #
1$
b11101001 &
#5060000000
0!
0$
#5070000000
1!
b11101010 #
1$
b11101010 &
#5080000000
0!
0$
#5090000000
1!
b11101011 #
1$
b11101011 &
#5100000000
0!
0$
#5110000000
1!
b11101100 #
1$
b11101100 &
#5120000000
0!
0$
#5130000000
1!
b11101101 #
1$
b11101101 &
#5140000000
0!
0$
#5150000000
1!
b11101110 #
1$
b11101110 &
#5160000000
0!
0$
#5170000000
1!
b11101111 #
1$
b11101111 &
#5180000000
0!
0$
#5190000000
1!
b11110000 #
1$
b11110000 &
#5200000000
0!
0$
#5210000000
1!
b11110001 #
1$
b11110001 &
#5220000000
0!
0$
#5230000000
1!
b11110010 #
1$
b11110010 &
#5240000000
0!
0$
#5250000000
1!
b11110011 #
1$
b11110011 &
#5260000000
0!
0$
#5270000000
1!
b11110100 #
1$
b11110100 &
#5280000000
0!
0$
#5290000000
1!
b11110101 #
1$
b11110101 &
#5300000000
0!
0$
#5310000000
1!
b11110110 #
1$
b11110110 &
#5320000000
0!
0$
#5330000000
1!
b11110111 #
1$
b11110111 &
#5340000000
0!
0$
#5350000000
1!
b11111000 #
1$
b11111000 &
#5360000000
0!
0$
#5370000000
1!
b11111001 #
1$
b11111001 &
#5380000000
0!
0$
#5390000000
1!
b11111010 #
1$
b11111010 &
#5400000000
0!
0$
#5410000000
1!
b11111011 #
1$
b11111011 &
#5420000000
0!
0$
#5430000000
1!
b11111100 #
1$
b11111100 &
#5440000000
0!
0$
#5450000000
1!
b11111101 #
1$
b11111101 &
#5460000000
0!
0$
#5470000000
1!
b11111110 #
1$
b11111110 &
#5480000000
0!
0$
#5490000000
1!
b11111111 #
1$
b11111111 &
