2/test_benchs/full_adder_test_bench/full_adder_dataflow.vhd
--------------------------------------------
-- Module Name: full_adder_dataflow
--------------------------------------------

library IEEE;
use IEEE.STD_LOGIC_1164.ALL;

Entity full_adder Is
port (
		x : in STD_LOGIC;
		y : in STD_LOGIC;
		cin : in STD_LOGIC;
        s : out STD_LOGIC;
        cout: out STD_LOGIC
	);
end full_adder;

Architecture behavior of full_adder Is

Signal x_y_cin : STD_LOGIC_VECTOR(2 downto 0);

begin        
		x_y_cin <= x & y & cin;

		--- ---------------------------
        --- TABLA DE VERDAD FULL_ADDER
		--- ---------------------------
		--- | x | y | cin || s | cout |
		--- ---------------------------
		--- | 0 | 0 |  0  || 0 |  0   |
		--- | 0 | 0 |  1  || 1 |  0   |
		--- | 0 | 1 |  0  || 1 |  0   |
		--- | 0 | 1 |  1  || 0 |  1   |
		--- | 1 | 0 |  0  || 1 |  0   |
		--- | 1 | 0 |  1  || 0 |  1   |
		--- | 1 | 1 |  0  || 0 |  1   |
		--- | 1 | 1 |  1  || 1 |  1   |
		--- ---------------------------


		-- Casos usando Selective Signal Assignment

		-- with chooser_expression select
        --   target <= expression when choices,
        --   ...
        --   expression when choices;

        with x_y_cin select
          s <= '1' when "001",
               '1' when "010",
               '1' when "100",
               '1' when "111",
               '0' when others;
        
        with x_y_cin select
          cout <= '1' when "011",
                  '1' when "101",
                  '1' when "110",
                  '1' when "111",
                  '0' when others;

end behavior;

2/test_benchs/full_adder_test_bench/full_adder_dataflow_tb2.vhd
--------------------------------------------
-- Module Name: halfadder_bahavioral_tb
--------------------------------------------

library IEEE;
use IEEE.STD_LOGIC_1164.ALL;
use IEEE.STD_LOGIC_ARITH.ALL;
use IEEE.STD_LOGIC_UNSIGNED.ALL;


Entity full_adder_dataflow_tb Is
end full_adder_dataflow_tb;

Architecture behavior of full_adder_dataflow_tb Is
	Component full_adder
	port (
		  x : in STD_LOGIC;
		  y : in STD_LOGIC;
		  cin : in STD_LOGIC;
          s : out STD_LOGIC;
          cout: out STD_LOGIC
		);	
	End Component;
	
	Signal test_vector 	: STD_LOGIC_VECTOR(2 DOWNTO 0) := "000";
	Signal s_sig    	: STD_LOGIC;
	Signal cout_sig    	: STD_LOGIC;


	
begin 
	DUT:  full_adder PORT MAP (
		x => test_vector(2),
		y => test_vector(1),
		cin => test_vector(0),
		s => s_sig,
		cout => cout_sig
	);
	

	testing: process
	-- Simple Testbench: Asignacion manual de estimulos
	constant PERIOD: time := 20 ns;
	begin
		test_vector <= "000";
		wait for PERIOD;
		test_vector <= "001";
		wait for PERIOD;
		test_vector <= "010";
		wait for PERIOD;
		test_vector <= "011";
		wait for PERIOD;
		test_vector <= "100";
		wait for PERIOD;
		test_vector <= "101";
		wait for PERIOD;
		test_vector <= "110";
		wait for PERIOD;
		test_vector <= "111";
		wait for PERIOD;
		wait;
	end process testing;
end behavior;

2/test_benchs/full_adder_test_bench/full_adder_dataflow_tb_results.vcd
$date
  Thu Jul 25 17:43:56 2019
$end
$version
  GHDL v0
$end
$timescale
  1 fs
$end
$scope module standard $end
$upscope $end
$scope module std_logic_1164 $end
$upscope $end
$scope module numeric_std $end
$upscope $end
$scope module textio $end
$upscope $end
$scope module full_adder_dataflow_tb $end
$var reg 3 ! test_vector[2:0] $end
$var reg 1 " s_sig $end
$var reg 1 # cout_sig $end
$scope module dut $end
$var reg 1 $ x $end
$var reg 1 % y $end
$var reg 1 & cin $end
$var reg 1 ' s $end
$var reg 1 ( cout $end
$var reg 3 ) x_y_cin[2:0] $end
$upscope $end
$upscope $end
$enddefinitions $end
#0
b000 !
0"
0#
0$
0%
0&
0'
0(
b000 )
#20000000
b001 !
1"
1&
1'
b001 )
#40000000
b010 !
1%
0&
b010 )
#60000000
b011 !
0"
1#
1&
0'
1(
b011 )
#80000000
b100 !
1"
0#
1$
0%
0&
1'
0(
b100 )
#100000000
b101 !
0"
1#
1&
0'
1(
b101 )
#120000000
b110 !
1%
0&
b110 )
#140000000
b111 !
1"
1&
1'
b111 )
