3/miselanea_ejemplos/ejemplo15/mux8.vhd
library IEEE;
use IEEE.STD_LOGIC_1164.all;
use IEEE.NUMERIC_STD_UNSIGNED.all;

entity mux8 is
	port(d : in  STD_LOGIC_VECTOR(7 downto 0);
	     s : in  STD_LOGIC_VECTOR(2 downto 0);
	     y : out STD_LOGIC);
end;

architecture synth of mux8 is
begin
	y <= d(TO_INTEGER(s));
end;

3/miselanea_ejemplos/ejemplo15/mux8_tb.vhd
library ieee;
use ieee.std_logic_1164.all;
use ieee.numeric_std.all;
use ieee.numeric_std_unsigned.all;


entity mux8_tb is
end entity mux8_tb;

architecture RTL of mux8_tb is
	component mux8
		port(
			d : in  STD_LOGIC_VECTOR(7 downto 0);
			s : in  STD_LOGIC_VECTOR(2 downto 0);
			y : out STD_LOGIC
		);
	end component mux8;
	
	signal d : std_logic_vector(7 downto 0) := "10001101";
	signal s : std_logic_vector(2 downto 0) := "000";
	signal y : std_logic;
	
	constant T : time := 10 ns;
	
	
begin
	DUT:mux8
		port map(
			d => d,
			s => s,
			y => y
		);
		
	stimulus : process is
	begin
		for i in 0 to 7 loop
			s <= std_logic_vector(to_unsigned(i,s'length));
			wait for T;			
		end loop;
		wait;		
	end process stimulus;
	
end architecture RTL;

3/miselanea_ejemplos/ejemplo15/mux8_wf.vcd
$date
  Fri Mar 27 10:14:07 2020
$end
$version
  GHDL v0
$end
$timescale
  1 fs
$end
$scope module standard $end
$upscope $end
$scope module textio $end
$upscope $end
$scope module std_logic_1164 $end
$upscope $end
$scope module numeric_std $end
$upscope $end
$scope module numeric_std_unsigned $end
$upscope $end
$scope module mux8_tb $end
$var reg 8 ! d[7:0] $end
$var reg 3 " s[2:0] $end
$var reg 1 # y $end
$scope module dut $end
$var reg 8 $ d[7:0] $end
$var reg 3 % s[2:0] $end
$var reg 1 & y $end
$upscope $end
$upscope $end
$enddefinitions $end
#0
b10001101 !
b000 "
1#
b10001101 $
b000 %
1&
#10000000
b001 "
0#
b001 %
0&
#20000000
b010 "
1#
b010 %
1&
#30000000
b011 "
b011 %
#40000000
b100 "
0#
b100 %
0&
#50000000
b101 "
b101 %
#60000000
b110 "
b110 %
#70000000
b111 "
1#
b111 %
1&
