5/ejemplo6/moore/seq_detector.vhd
library IEEE;
use IEEE.STD_LOGIC_1164.ALL;
use IEEE.NUMERIC_STD.ALL; 
use IEEE.STD_LOGIC_UNSIGNED.ALL;
use IEEE.STD_LOGIC_ARITH.ALL;

entity seq_detector is
    Port ( Clock : in STD_LOGIC;
           Reset : in STD_LOGIC;
           w : in STD_LOGIC;
           z : out STD_LOGIC);
end seq_detector;

architecture seq_detector_arch of seq_detector is

    type STATES is (A, B, C);
    signal current_state, next_state : STATES;

begin
    -------------------------------------------------------------------
    STATE_MEMORY: process(Clock, Reset)
    begin
        if Reset = '1' then
          current_state <= A;        
        elsif Clock'event and Clock='1' then
          current_state <= next_state;            
        end if;
    end process;
    -------------------------------------------------------------------
    NEXT_STATE_LOGIC : process(current_state, w)
    begin
      case (current_state) is
        when A => 
          if (w = '1') then
            next_state <= B;
          else
          next_state <= A;
          end if;
        when B => 
          if (w ='1') then
            next_state <= C;
          else
            next_state <= A;
          end if;
        when C => 
          if (w ='1') then
            next_state <= C;
          else
            next_state <= A;
          end if;
      end case;
    end process;
    -------------------------------------------------------------------
    OUTPUT_LOGIC : process (current_state)
    begin
      case (current_state) is
        when A => 
          z <= '0';
        when B => 
          z <= '0';
        when C => 
          z <= '1';
      end case;
    end process;    
end architecture;

5/ejemplo6/mealy/2/seq_detector_tb.vhd
library IEEE;
use IEEE.STD_LOGIC_1164.ALL;
use IEEE.NUMERIC_STD.ALL; 
use IEEE.STD_LOGIC_UNSIGNED.ALL;
use IEEE.STD_LOGIC_ARITH.ALL;

entity seq_detector_tb is
end seq_detector_tb;

architecture behavioral of seq_detector_tb is

    -- declaraciones modelo FSM

    signal Clock, Reset, w, z: STD_LOGIC;   

    component seq_detector is
      Port ( Clock : in STD_LOGIC;
             Reset : in STD_LOGIC;
             w : in STD_LOGIC;
             z : out STD_LOGIC);
    end component;

begin

  DUT: seq_detector
	Port map (
    Clock => Clock,
    Reset => Reset,
    w => w,
    z => z
  );
  
  Clock_stimulus: process
  begin
    Clock <= '0';
    wait for 10 ns;
    Clock <= '1';
    wait for 10 ns;
  end process;

  Reset_stimulus: process
  begin
    Reset <= '1';
    wait for 20 ns;     -- 20 ns
    Reset <= '0';
    wait;  
  end  process;

  Press_stimulus: process
  begin
    w <= '0';
    wait for 32 ns;     -- 32 ns    
    w <= '1';
    wait for 20 ns;     -- 52 ns    
    w <= '0';
    wait for 20 ns;     -- 72 ns    
    w <= '1';
    wait for 40 ns;     -- 112 ns    
    w <= '0';
    wait for 20 ns;     -- 132 ns    
    w <= '1';
    wait for 60 ns;     -- 192 ns  
    w <= '0';
    wait for 20 ns;     -- 212 ns   
    w <= '1';
    wait;
  end process;
   
end architecture;

5/ejemplo6/mealy/2/seq_detector_tb_results.vcd
$date
  Mon Jul  6 01:05:12 2020
$end
$version
  GHDL v0
$end
$timescale
  1 fs
$end
$scope module standard $end
$upscope $end
$scope module std_logic_1164 $end
$upscope $end
$scope module numeric_std $end
$upscope $end
$scope module std_logic_arith $end
$upscope $end
$scope module std_logic_unsigned $end
$upscope $end
$scope module seq_detector_tb $end
$var reg 1 ! clock $end
$var reg 1 " reset $end
$var reg 1 # w $end
$var reg 1 $ z $end
$scope module dut $end
$var reg 1 % clock $end
$var reg 1 & reset $end
$var reg 1 ' w $end
$var reg 1 ( z $end
$comment current_state is not handled $end
$comment next_state is not handled $end
$upscope $end
$upscope $end
$enddefinitions $end
#0
0!
1"
0#
0$
0%
1&
0'
0(
#10000000
1!
1%
#20000000
0!
0"
0%
0&
#30000000
1!
1%
#32000000
1#
1'
#40000000
0!
0%
#50000000
1!
1$
1%
1(
#52000000
0#
0$
0'
0(
#60000000
0!
0%
#70000000
1!
1%
#72000000
1#
1'
#80000000
0!
0%
#90000000
1!
1$
1%
1(
#100000000
0!
0%
#110000000
1!
1%
#112000000
0#
0$
0'
0(
#120000000
0!
0%
#130000000
1!
1%
#132000000
1#
1'
#140000000
0!
0%
#150000000
1!
1$
1%
1(
#160000000
0!
0%
#170000000
1!
1%
#180000000
0!
0%
#190000000
1!
1%
#192000000
0#
0$
0'
0(
#200000000
0!
0%
#210000000
1!
1%
#212000000
1#
1'
#220000000
0!
0%
#230000000
1!
1$
1%
1(
