5/example3/moore/moore.vhd
library IEEE;
use IEEE.STD_LOGIC_1164.ALL;
use IEEE.NUMERIC_STD.ALL; 
use IEEE.STD_LOGIC_UNSIGNED.ALL;
use IEEE.STD_LOGIC_ARITH.ALL;

entity FSM_MOORE is
    Port ( reset : in STD_LOGIC;
           clk : in STD_LOGIC;
           ain : in STD_LOGIC_VECTOR(1 DOWNTO 0);
           yout : out STD_LOGIC);
end FSM_MOORE;

architecture Behavioral of FSM_MOORE is

    -- declaraciones modelo FSM
    type STATES is (S0, S1, S2, S3, S4, S5, S6, S7);
    signal state, next_state: STATES;

begin

    -- registro de estados
    SYNC_PROC: process(clk)    
    begin
        if clk'event and clk='1' then
            if reset='1' then 
                state <= S0;
            else 
                state <= next_state;
            end if;
         end if;
    end process;

    OUTPUT_DECODE : process (state)
    begin
      case (state) is 
         when S0 =>
           yout <= '0';
         when S1 =>
           yout <= '1';
         when S2 =>
           yout <= '0';
         when S3 =>
           yout <= '0';
         when S4 =>
           yout <= '0';
         when S5 =>
           yout <= '1';
         when S6 =>
           yout <= '1';
         when S7 =>
           yout <= '1';
         when others =>
           yout <= '0';
      end case;
    end process;


    -- Lógica de estado siguiente (circuito combinacional)

    NEXT_STATE_DECODE : process (state, ain)
    begin
      next_state <= S0;
      case (state) is
        -- S0 --
        when S0 =>                       
          if (ain = "00") then    -- 00
            next_state <= S0;
          elsif (ain = "01") then -- 01
            next_state <= S2;
          elsif (ain = "11") then -- 11
            next_state <= S3;
          else                    -- 10
            next_state <= S4;
          end if;
        -- S1 --
        when S1 =>                       
          if (ain = "00") then    -- 00
            next_state <= S1;
          elsif (ain = "01") then -- 01
            next_state <= S6;
          elsif (ain = "11") then -- 11
            next_state <= S7;
          else                    -- 10
            next_state <= S5;
          end if;
        -- S2 --
        when S2 =>                       
          if (ain = "00") then    -- 00
            next_state <= S0;
          elsif (ain = "01") then -- 01
            next_state <= S2;
          elsif (ain = "11") then -- 11
            next_state <= S3;
          else                    -- 10
            next_state <= S4;
          end if;
        -- S3 --
        when S3 =>                       
          if (ain = "00") then    -- 00
            next_state <= S1;
          elsif (ain = "01") then -- 01
            next_state <= S2;
          elsif (ain = "11") then -- 11
            next_state <= S3;
          else                    -- 10
            next_state <= S4;
          end if;
        -- S4 --
        when S4 =>                       
          if (ain = "00") then    -- 00
            next_state <= S1;
          elsif (ain = "01") then -- 01
            next_state <= S2;
          elsif (ain = "11") then -- 11
            next_state <= S3;
          else                    -- 10
            next_state <= S4;
          end if;
        -- S5 --
        when S5 =>                       
          if (ain = "00") then    -- 00
            next_state <= S0;
          elsif (ain = "01") then -- 01
            next_state <= S6;
          elsif (ain = "11") then -- 11
            next_state <= S7;
          else                    -- 10
            next_state <= S5;
          end if;
        -- S6 --
        when S6 =>                       
          if (ain = "00") then    -- 00
            next_state <= S0;
          elsif (ain = "01") then -- 01
            next_state <= S6;
          elsif (ain = "11") then -- 11
            next_state <= S7;
          else                    -- 10
            next_state <= S5;
          end if;
        -- S7 --
        when S7 =>                       
          if (ain = "00") then    -- 00
            next_state <= S1;
          elsif (ain = "01") then -- 01
            next_state <= S6;
          elsif (ain = "11") then -- 11
            next_state <= S7;
          else                    -- 10
            next_state <= S5;
          end if;          
        end case;
    end process;
end Behavioral;

5/example3/moore/moore_tb.vhd
library IEEE;
use IEEE.STD_LOGIC_1164.ALL;
use IEEE.NUMERIC_STD.ALL; 
use IEEE.STD_LOGIC_UNSIGNED.ALL;
use IEEE.STD_LOGIC_ARITH.ALL;

entity FSM_MOORE_TB is
end FSM_MOORE_TB;

architecture Behavioral of FSM_MOORE_TB is

    -- declaraciones modelo FSM

    signal clk_int, reset_int, yout_int: STD_LOGIC;
    signal ain_int: STD_LOGIC_VECTOR(1 DOWNTO 0);
  
    component FSM_MOORE is
      Port ( reset : in STD_LOGIC;
             clk : in STD_LOGIC;
             ain : in STD_LOGIC_VECTOR(1 DOWNTO 0);            
             yout : out STD_LOGIC);
    end component;

begin

  DUT: FSM_MOORE
	Port map (
    reset => reset_int,
    clk => clk_int,
    ain => ain_int,
    yout => yout_int
  );
  

  clk_gen_proc: process
  begin
    clk_int <= '0';
    wait for 5 ns;
    clk_int <= '1';
    wait for 5 ns;
  end process clk_gen_proc;

  -- Nota: Se puede hacer un proceso a parte para el reset
  data_gen_proc: process
  begin
    ain_int <= "00";    -- 0 ns
    reset_int <= '1';
    wait for 20 ns;    -- 20 ns
    reset_int <= '0';
    wait for 20 ns;    -- 40 ns
    ain_int <= "11";
    wait for 10 ns;    -- 50 ns
    ain_int <= "10";
    wait for 10 ns;    -- 60 ns
    ain_int <= "00";
    wait for 20 ns;    -- 80 ns
    ain_int <= "10";
    wait for 10 ns;    -- 90 ns
    ain_int <= "00";
    wait for 10 ns;    -- 100 ns
    ain_int <= "11";
    wait for 10 ns;    -- 110 ns
    ain_int <= "00";
    wait for 10 ns;    -- 120 ns
    ain_int <= "01";
    wait for 10 ns;    -- 130 ns
    ain_int <= "00";
    wait for 10 ns;    -- 140 ns
    ain_int <= "10";
    wait for 10 ns;    -- 150 ns
    ain_int <= "11";
    wait for 10 ns;    -- 160 ns
    ain_int <= "00";
    wait for 10 ns;    -- 170 ns
    reset_int <= '1';
    wait for 10 ns;    -- 180 ns
    reset_int <= '0';
    wait for 10 ns;    -- 190 ns
    ain_int <= "10";
    wait for 30 ns;    -- 220 ns
    ain_int <= "00";
    wait for 30 ns;    -- 250 ns
  end process data_gen_proc;
   
end Behavioral;

5/parte2/moore/FSM_MOORE_TB_results.vcd
$date
  Sun Sep 22 03:12:28 2019
$end
$version
  GHDL v0
$end
$timescale
  1 fs
$end
$scope module standard $end
$upscope $end
$scope module std_logic_1164 $end
$upscope $end
$scope module numeric_std $end
$upscope $end
$scope module std_logic_arith $end
$upscope $end
$scope module std_logic_unsigned $end
$upscope $end
$scope module fsm_moore_tb $end
$var reg 1 ! clk_int $end
$var reg 1 " reset_int $end
$var reg 1 # yout_int $end
$var reg 2 $ ain_int[1:0] $end
$scope module dut $end
$var reg 1 % reset $end
$var reg 1 & clk $end
$var reg 2 ' ain[1:0] $end
$var reg 1 ( yout $end
$comment state is not handled $end
$comment next_state is not handled $end
$upscope $end
$upscope $end
$enddefinitions $end
#0
0!
1"
0#
b00 $
1%
0&
b00 '
0(
#5000000
1!
1&
#10000000
0!
0&
#15000000
1!
1&
#20000000
0!
0"
0%
0&
#25000000
1!
1&
#30000000
0!
0&
#35000000
1!
1&
#40000000
0!
b11 $
0&
b11 '
#45000000
1!
1&
#50000000
0!
b10 $
0&
b10 '
#55000000
1!
1&
#60000000
0!
b00 $
0&
b00 '
#65000000
1!
1#
1&
1(
#70000000
0!
0&
#75000000
1!
1&
#80000000
0!
b10 $
0&
b10 '
#85000000
1!
1&
#90000000
0!
b00 $
0&
b00 '
#95000000
1!
0#
1&
0(
#100000000
0!
b11 $
0&
b11 '
#105000000
1!
1&
#110000000
0!
b00 $
0&
b00 '
#115000000
1!
1#
1&
1(
#120000000
0!
b01 $
0&
b01 '
#125000000
1!
1&
#130000000
0!
b00 $
0&
b00 '
#135000000
1!
0#
1&
0(
#140000000
0!
b10 $
0&
b10 '
#145000000
1!
1&
#150000000
0!
b11 $
0&
b11 '
#155000000
1!
1&
#160000000
0!
b00 $
0&
b00 '
#165000000
1!
1#
1&
1(
#170000000
0!
1"
1%
0&
#175000000
1!
0#
1&
0(
#180000000
0!
0"
0%
0&
#185000000
1!
1&
#190000000
0!
b10 $
0&
b10 '
#195000000
1!
1&
#200000000
0!
0&
#205000000
1!
1&
#210000000
0!
0&
#215000000
1!
1&
#220000000
0!
b00 $
0&
b00 '
#225000000
1!
1#
1&
1(
#230000000
0!
0&
#235000000
1!
1&
#240000000
0!
0&
#245000000
1!
1&
#250000000
0!
1"
1%
0&
